Workbook
Name ___DAT10: #REF!
Name ___DAT11: #REF!
Name ___DAT12: #REF!
Name ___DAT13: #REF!
Name ___DAT14: #REF!
Name ___DAT15: #REF!
Name ___DAT16: #REF!
Name ___DAT17: #REF!
Name ___DAT18: #REF!
Name ___DAT19: #REF!
Name ___DAT2: #REF!
Name ___DAT20: #REF!
Name ___DAT21: #REF!
Name ___DAT22: #REF!
Name ___DAT23: #REF!
Name ___DAT24: #REF!
Name ___DAT25: #REF!
Name ___DAT3: #REF!
Name ___DAT4: #REF!
Name ___DAT5: #REF!
Name ___DAT6: #REF!
Name ___DAT7: #REF!
Name ___DAT8: #REF!
Name ___DAT9: #REF!
Name __DAT1: #REF!
Name __DAT10: #REF!
Name __DAT11: #REF!
Name __DAT12: #REF!
Name __DAT13: #REF!
Name __DAT14: #REF!
Name __DAT15: #REF!
Name __DAT16: #REF!
Name __DAT17: #REF!
Name __DAT18: #REF!
Name __DAT19: #REF!
Name __DAT2: #REF!
Name __DAT20: #REF!
Name __DAT21: #REF!
Name __DAT22: #REF!
Name __DAT23: #REF!
Name __DAT24: #REF!
Name __DAT25: #REF!
Name __DAT3: #REF!
Name __DAT4: #REF!
Name __DAT5: #REF!
Name __DAT6: #REF!
Name __DAT7: #REF!
Name __DAT8: #REF!
Name __DAT9: #REF!
Name _DAT1: #REF!
Name _DAT10: #REF!
Name _DAT11: #REF!
Name _DAT12: #REF!
Name _DAT13: #REF!
Name _DAT14: #REF!
Name _DAT15: #REF!
Name _DAT16: #REF!
Name _DAT17: #REF!
Name _DAT18: #REF!
Name _DAT19: #REF!

Sheet BS-Liabilities
A1: Liabilities | B1: Main Category | C1: Sub Category | D1: Particulars | E1: Item Number | F1: 46174 | G1: 46082 | H1: Variance | I1: Reasons | K1: 45901 | L1: 45992
A2: Current liabilities ( ≤ 1 year) | B2: Trade payables | C2: Trade payables | D2: Trade payables - 3rd, B-c, B-f | E2: 20100 | F2: =IFERROR(VLOOKUP(E2,'[9]SAP Input-BS'!$A$5:$F$502,5,0),0) -> -6.5071733e+09 | G2: =IFERROR(VLOOKUP(E2,'[10]SAP Input-BS'!$A$5:$F$500,5,0),0) -> -5.0483844e+09 | H2: =F2-G2 -> -1.4587889e+09 | J2: Schedule | K2: =IFERROR(VLOOKUP(E2,'[11]SAP Input-BS'!$A$5:$E$500,5,0),0) -> -6.3165899e+09 | L2: -7.9635468e+09
A3: Current liabilities ( ≤ 1 year) | B3: Trade payables | C3: Trade payables | D3: Trade payables - K | E3: 20120 | F3: =IFERROR(VLOOKUP(E3,'[9]SAP Input-BS'!$A$5:$F$502,5,0),0) -> -4830249126 | G3: =IFERROR(VLOOKUP(E3,'[10]SAP Input-BS'!$A$5:$F$500,5,0),0) -> -4.0158494e+09 | H3: =F3-G3 -> -8.143997e+08 | K3: =IFERROR(VLOOKUP(E3,'[11]SAP Input-BS'!$A$5:$E$500,5,0),0) -> -2.9790446e+09 | L3: -4.2969963e+09
A4: Current liabilities ( ≤ 1 year) | B4: Trade payables | C4: Trade payables | D4: License payables - K | E4: 20125 | F4: =IFERROR(VLOOKUP(E4,'[9]SAP Input-BS'!$A$5:$F$502,5,0),0) -> -28893230 | G4: =IFERROR(VLOOKUP(E4,'[10]SAP Input-BS'!$A$5:$F$500,5,0),0) -> -8508157.9 | H4: =F4-G4 -> -20385072 | K4: =IFERROR(VLOOKUP(E4,'[11]SAP Input-BS'!$A$5:$E$500,5,0),0) -> -1.2881517e+08 | L4: -2.3793154e+08
A5: Current liabilities ( ≤ 1 year) | B5: Trade payables | C5: Trade payables | D5: Trade payables - N | E5: 20140 | F5: =IFERROR(VLOOKUP(E5,'[9]SAP Input-BS'!$A$5:$F$502,5,0),0) -> -44746309 | G5: =IFERROR(VLOOKUP(E5,'[10]SAP Input-BS'!$A$5:$F$500,5,0),0) -> -44746308 | H5: =F5-G5 -> -0.71 | J5: Schedule | K5: =IFERROR(VLOOKUP(E5,'[11]SAP Input-BS'!$A$5:$E$500,5,0),0) -> 0 | L5: -44746309
A6: Current liabilities ( ≤ 1 year) | B6: Trade payables | C6: Trade payables | D6: Trade payables - B-a | E6: 20160 | F6: =IFERROR(VLOOKUP(E6,'[9]SAP Input-BS'!$A$5:$F$502,5,0),0) -> 0 | G6: =IFERROR(VLOOKUP(E6,'[10]SAP Input-BS'!$A$5:$F$500,5,0),0) -> 0 | H6: =F6-G6 -> 0 | K6: =IFERROR(VLOOKUP(E6,'[11]SAP Input-BS'!$A$5:$E$500,5,0),0) -> 0 | L6: 0
A7: Current liabilities ( ≤ 1 year) | B7: Trade payables | C7: Trade payables | D7: Total: Trade payables | E7: 20179 | F7: =IFERROR(VLOOKUP(E7,'[9]SAP Input-BS'!$A$5:$F$502,5,0),0) -> -1.1243962e+10 | G7: =IFERROR(VLOOKUP(E7,'[10]SAP Input-BS'!$A$5:$F$500,5,0),0) -> -9.1174883e+09 | H7: =F7-G7 -> -2.1264736e+09 | K7: =IFERROR(VLOOKUP(E7,'[11]SAP Input-BS'!$A$5:$E$500,5,0),0) -> -9.4244496e+09 | L7: -1.2543221e+10
A8: Current liabilities ( ≤ 1 year) | B8: Trade payables | C8: Trade payables | D8: Notes payable | E8: 20180 | F8: =IFERROR(VLOOKUP(E8,'[9]SAP Input-BS'!$A$5:$F$502,5,0),0) -> 0 | G8: =IFERROR(VLOOKUP(E8,'[10]SAP Input-BS'!$A$5:$F$500,5,0),0) -> 0 | H8: =F8-G8 -> 0 | K8: =IFERROR(VLOOKUP(E8,'[11]SAP Input-BS'!$A$5:$E$500,5,0),0) -> 0 | L8: 0
A9: Current liabilities ( ≤ 1 year) | B9: Trade payables | C9: Trade payables | D9: Total: Trade payables and notes payable | E9: LC_AP | F9: =IFERROR(VLOOKUP(E9,'[9]SAP Input-BS'!$A$5:$F$502,5,0),0) -> -1.1411062e+10 | G9: =IFERROR(VLOOKUP(E9,'[10]SAP Input-BS'!$A$5:$F$500,5,0),0) -> -9.1174883e+09 | H9: =F9-G9 -> -2.2935737e+09 | K9: =IFERROR(VLOOKUP(E9,'[11]SAP Input-BS'!$A$5:$E$500,5,0),0) -> -9.4244496e+09 | L9: -1.2543221e+10
A10: Current liabilities ( ≤ 1 year) | B10: Lease liabilities (lessee) ≤ 1 y | C10: Lease liabilities (lessee) ≤ 1 y | D10: Lease liabilities (lessee) ≤ 1 y | E10: 21500 | F10: =IFERROR(VLOOKUP(E10,'[9]SAP Input-BS'!$A$5:$F$502,5,0),0) -> -1.7554863e+09 | G10: =IFERROR(VLOOKUP(E10,'[10]SAP Input-BS'!$A$5:$F$500,5,0),0) -> -2.6661777e+09 | H10: =F10-G10 -> 9.1069146e+08 | K10: =IFERROR(VLOOKUP(E10,'[11]SAP Input-BS'!$A$5:$E$500,5,0),0) -> -1.1066156e+09 | L10: -2.2974229e+09
A11: Current liabilities ( ≤ 1 year) | B11: Lease liabilities (lessee) ≤ 1 y | C11: Lease liabilities (lessee) ≤ 1 y | D11: Total: Lease liabilities (lessee) ≤ 1 y | E11: LC_LL | F11: =IFERROR(VLOOKUP(E11,'[9]SAP Input-BS'!$A$5:$F$502,5,0),0) -> -1.7554863e+09 | G11: =IFERROR(VLOOKUP(E11,'[10]SAP Input-BS'!$A$5:$F$500,5,0),0) -> -2.6661777e+09 | H11: =F11-G11 -> 9.1069146e+08 | K11: =IFERROR(VLOOKUP(E11,'[11]SAP Input-BS'!$A$5:$E$500,5,0),0) -> -1.1066156e+09 | L11: -2.2974229e+09
A12: Current liabilities ( ≤ 1 year) | B12: Financial liabilities | D12: Bonds ≤ 1 y | E12: 20010 | F12: =IFERROR(VLOOKUP(E12,'[9]SAP Input-BS'!$A$5:$F$502,5,0),0) -> 0 | G12: =IFERROR(VLOOKUP(E12,'[10]SAP Input-BS'!$A$5:$F$500,5,0),0) -> 0 | H12: =F12-G12 -> 0 | K12: =IFERROR(VLOOKUP(E12,'[11]SAP Input-BS'!$A$5:$E$500,5,0),0) -> 0 | L12: 0
A13: Current liabilities ( ≤ 1 year) | B13: Financial liabilities | D13: Liabilities with banks ≤ 1 y | E13: 20020 | F13: =IFERROR(VLOOKUP(E13,'[9]SAP Input-BS'!$A$5:$F$502,5,0),0) -> 0 | G13: =IFERROR(VLOOKUP(E13,'[10]SAP Input-BS'!$A$5:$F$500,5,0),0) -> 0 | H13: =F13-G13 -> 0 | K13: =IFERROR(VLOOKUP(E13,'[11]SAP Input-BS'!$A$5:$E$500,5,0),0) -> 0 | L13: 0
A14: Current liabilities ( ≤ 1 year) | B14: Financial liabilities | D14: Commercial papers ≤ 1 y | E14: 20030 | F14: =IFERROR(VLOOKUP(E14,'[9]SAP Input-BS'!$A$5:$F$502,5,0),0) -> 0 | G14: =IFERROR(VLOOKUP(E14,'[10]SAP Input-BS'!$A$5:$F$500,5,0),0) -> 0 | H14: =F14-G14 -> 0 | K14: =IFERROR(VLOOKUP(E14,'[11]SAP Input-BS'!$A$5:$E$500,5,0),0) -> 0 | L14: 0
A15: Current liabilities ( ≤ 1 year) | B15: Financial liabilities | D15: Promissory note loans ≤ 1 y | E15: 20035 | F15: =IFERROR(VLOOKUP(E15,'[9]SAP Input-BS'!$A$5:$F$502,5,0),0) -> 0 | G15: =IFERROR(VLOOKUP(E15,'[10]SAP Input-BS'!$A$5:$F$500,5,0),0) -> 0 | H15: =F15-G15 -> 0 | K15: =IFERROR(VLOOKUP(E15,'[11]SAP Input-BS'!$A$5:$E$500,5,0),0) -> 0 | L15: 0
A16: Current liabilities ( ≤ 1 year) | B16: Financial liabilities | D16: Other financial liabilities ≤ 1 y | E16: 20040 | F16: =IFERROR(VLOOKUP(E16,'[9]SAP Input-BS'!$A$5:$F$502,5,0),0) -> 0 | G16: =IFERROR(VLOOKUP(E16,'[10]SAP Input-BS'!$A$5:$F$500,5,0),0) -> 0 | H16: =F16-G16 -> 0 | K16: =IFERROR(VLOOKUP(E16,'[11]SAP Input-BS'!$A$5:$E$500,5,0),0) -> 0 | L16: 0
A17: Current liabilities ( ≤ 1 year) | B17: Financial liabilities | D17: Total: Financial liabilities ≤ 1 y | E17: 20099 | F17: =IFERROR(VLOOKUP(E17,'[9]SAP Input-BS'!$A$5:$F$502,5,0),0) -> 0 | G17: =IFERROR(VLOOKUP(E17,'[10]SAP Input-BS'!$A$5:$F$500,5,0),0) -> 0 | H17: =F17-G17 -> 0 | K17: =IFERROR(VLOOKUP(E17,'[11]SAP Input-BS'!$A$5:$E$500,5,0),0) -> 0 | L17: 0
A18: Current liabilities ( ≤ 1 year) | B18: Loans ≤ 1 y | D18: Loans ≤ 1 y - 3rd, B-c, B-f | E18: 20300 | F18: =IFERROR(VLOOKUP(E18,'[9]SAP Input-BS'!$A$5:$F$502,5,0),0) -> 0 | G18: =IFERROR(VLOOKUP(E18,'[10]SAP Input-BS'!$A$5:$F$500,5,0),0) -> 0 | H18: =F18-G18 -> 0 | K18: =IFERROR(VLOOKUP(E18,'[11]SAP Input-BS'!$A$5:$E$500,5,0),0) -> 0 | L18: 0
A19: Current liabilities ( ≤ 1 year) | B19: Loans ≤ 1 y | D19: Loans ≤ 1 y - K | E19: 20320 | F19: =IFERROR(VLOOKUP(E19,'[9]SAP Input-BS'!$A$5:$F$502,5,0),0) -> 0 | G19: =IFERROR(VLOOKUP(E19,'[10]SAP Input-BS'!$A$5:$F$500,5,0),0) -> 0 | H19: =F19-G19 -> 0 | K19: =IFERROR(VLOOKUP(E19,'[11]SAP Input-BS'!$A$5:$E$500,5,0),0) -> 0 | L19: 0
A20: Current liabilities ( ≤ 1 year) | B20: Loans ≤ 1 y | D20: Loans ≤ 1 y - N | E20: 20340 | F20: =IFERROR(VLOOKUP(E20,'[9]SAP Input-BS'!$A$5:$F$502,5,0),0) -> 0 | G20: =IFERROR(VLOOKUP(E20,'[10]SAP Input-BS'!$A$5:$F$500,5,0),0) -> 0 | H20: =F20-G20 -> 0 | K20: =IFERROR(VLOOKUP(E20,'[11]SAP Input-BS'!$A$5:$E$500,5,0),0) -> 0 | L20: 0
A21: Current liabilities ( ≤ 1 year) | B21: Loans ≤ 1 y | D21: Loans ≤ 1 y - B-a | E21: 20360 | F21: =IFERROR(VLOOKUP(E21,'[9]SAP Input-BS'!$A$5:$F$502,5,0),0) -> 0 | G21: =IFERROR(VLOOKUP(E21,'[10]SAP Input-BS'!$A$5:$F$500,5,0),0) -> 0 | H21: =F21-G21 -> 0 | K21: =IFERROR(VLOOKUP(E21,'[11]SAP Input-BS'!$A$5:$E$500,5,0),0) -> 0 | L21: 0
A22: Current liabilities ( ≤ 1 year) | B22: Loans ≤ 1 y | D22: Total: Loans ≤ 1 y | E22: 20379 | F22: =IFERROR(VLOOKUP(E22,'[9]SAP Input-BS'!$A$5:$F$502,5,0),0) -> 0 | G22: =IFERROR(VLOOKUP(E22,'[10]SAP Input-BS'!$A$5:$F$500,5,0),0) -> 0 | H22: =F22-G22 -> 0 | K22: =IFERROR(VLOOKUP(E22,'[11]SAP Input-BS'!$A$5:$E$500,5,0),0) -> 0 | L22: 0
A23: Current liabilities ( ≤ 1 year) | B23: Financial clearing, cash pool | C23: Financial clearing, cash pool | D23: Financial clearing, cash pool - K | E23: 20420 | F23: =IFERROR(VLOOKUP(E23,'[9]SAP Input-BS'!$A$5:$F$502,5,0),0) -> 0 | G23: =IFERROR(VLOOKUP(E23,'[10]SAP Input-BS'!$A$5:$F$500,5,0),0) -> 0 | H23: =F23-G23 -> 0 | K23: =IFERROR(VLOOKUP(E23,'[11]SAP Input-BS'!$A$5:$E$500,5,0),0) -> 0 | L23: 0
A24: Current liabilities ( ≤ 1 year) | B24: Financial clearing, cash pool | C24: Financial clearing, cash pool | D24: Financial clearing, cash pool - N | E24: 20440 | F24: =IFERROR(VLOOKUP(E24,'[9]SAP Input-BS'!$A$5:$F$502,5,0),0) -> 0 | G24: =IFERROR(VLOOKUP(E24,'[10]SAP Input-BS'!$A$5:$F$500,5,0),0) -> 0 | H24: =F24-G24 -> 0 | K24: =IFERROR(VLOOKUP(E24,'[11]SAP Input-BS'!$A$5:$E$500,5,0),0) -> 0 | L24: 0
A25: Current liabilities ( ≤ 1 year) | B25: Financial clearing, cash pool | C25: Financial clearing, cash pool | D25: Financial clearing, cash pool - B-a | E25: 20460 | F25: =IFERROR(VLOOKUP(E25,'[9]SAP Input-BS'!$A$5:$F$502,5,0),0) -> 0 | G25: =IFERROR(VLOOKUP(E25,'[10]SAP Input-BS'!$A$5:$F$500,5,0),0) -> 0 | H25: =F25-G25 -> 0 | K25: =IFERROR(VLOOKUP(E25,'[11]SAP Input-BS'!$A$5:$E$500,5,0),0) -> 0 | L25: 0
A26: Current liabilities ( ≤ 1 year) | B26: Financial clearing, cash pool | C26: Financial clearing, cash pool | D26: Financial clearing, cash pool - B-c, B-f | E26: 20470 | F26: =IFERROR(VLOOKUP(E26,'[9]SAP Input-BS'!$A$5:$F$502,5,0),0) -> 0 | G26: =IFERROR(VLOOKUP(E26,'[10]SAP Input-BS'!$A$5:$F$500,5,0),0) -> 0 | H26: =F26-G26 -> 0 | K26: =IFERROR(VLOOKUP(E26,'[11]SAP Input-BS'!$A$5:$E$500,5,0),0) -> 0 | L26: 0
A27: Current liabilities ( ≤ 1 year) | B27: Financial clearing, cash pool | C27: Financial clearing, cash pool | D27: Total: Financial clearing, cash pool | E27: 20479 | F27: =IFERROR(VLOOKUP(E27,'[9]SAP Input-BS'!$A$5:$F$502,5,0),0) -> 0 | G27: =IFERROR(VLOOKUP(E27,'[10]SAP Input-BS'!$A$5:$F$500,5,0),0) -> 0 | H27: =F27-G27 -> 0 | K27: =IFERROR(VLOOKUP(E27,'[11]SAP Input-BS'!$A$5:$E$500,5,0),0) -> 0 | L27: 0
A28: Current liabilities ( ≤ 1 year) | B28: Financial liabilities ≤ 1 y | C28: Derivatives Outstanding | D28: Derivatives w/o hedge ≤ 1 y - 3rd | E28: 21305 | F28: =IFERROR(VLOOKUP(E28,'[9]SAP Input-BS'!$A$5:$F$502,5,0),0) -> -4.6308147e+08 | G28: =IFERROR(VLOOKUP(E28,'[10]SAP Input-BS'!$A$5:$F$500,5,0),0) -> -1425368884 | H28: =F28-G28 -> 9.6228741e+08 | J28: =(F28-G28)/87 -> 11060775 | K28: =IFERROR(VLOOKUP(E28,'[11]SAP Input-BS'!$A$5:$E$500,5,0),0) -> -7.3916284e+08 | L28: -5.6610601e+08
A29: Current liabilities ( ≤ 1 year) | B29: Financial liabilities ≤ 1 y | D29: Liabilities dividends - 3rd, B-c, B-f | E29: 21312 | F29: =IFERROR(VLOOKUP(E29,'[9]SAP Input-BS'!$A$5:$F$502,5,0),0) -> 0 | G29: =IFERROR(VLOOKUP(E29,'[10]SAP Input-BS'!$A$5:$F$500,5,0),0) -> 0 | H29: =F29-G29 -> 0 | K29: =IFERROR(VLOOKUP(E29,'[11]SAP Input-BS'!$A$5:$E$500,5,0),0) -> 0 | L29: 0
A30: Current liabilities ( ≤ 1 year) | B30: Financial liabilities ≤ 1 y | D30: Debtors with credit balances - 3rd, B-c, B-f | E30: 21314 | F30: =IFERROR(VLOOKUP(E30,'[9]SAP Input-BS'!$A$5:$F$502,5,0),0) -> 0 | G30: =IFERROR(VLOOKUP(E30,'[10]SAP Input-BS'!$A$5:$F$500,5,0),0) -> 0 | H30: =F30-G30 -> 0 | K30: =IFERROR(VLOOKUP(E30,'[11]SAP Input-BS'!$A$5:$E$500,5,0),0) -> 0 | L30: 0
A31: Current liabilities ( ≤ 1 year) | B31: Financial liabilities ≤ 1 y | D31: Liabilities accrued interest - 3rd, B-c, B-f | E31: 21315 | F31: =IFERROR(VLOOKUP(E31,'[9]SAP Input-BS'!$A$5:$F$502,5,0),0) -> 0 | G31: =IFERROR(VLOOKUP(E31,'[10]SAP Input-BS'!$A$5:$F$500,5,0),0) -> 0 | H31: =F31-G31 -> 0 | K31: =IFERROR(VLOOKUP(E31,'[11]SAP Input-BS'!$A$5:$E$500,5,0),0) -> 0 | L31: 0
A32: Current liabilities ( ≤ 1 year) | B32: Financial liabilities ≤ 1 y | C32: Withheld and Retention amount & Capital Creditors reclass | D32: Other financial liabilities ≤ 1 y - 3rd, B-c, B-f | E32: 21318 | F32: =IFERROR(VLOOKUP(E32,'[9]SAP Input-BS'!$A$5:$F$502,5,0),0) -> -8.7410343e+08 | G32: =IFERROR(VLOOKUP(E32,'[10]SAP Input-BS'!$A$5:$F$500,5,0),0) -> -4.1923078e+08 | H32: =F32-G32 -> -4.5487265e+08 | K32: =IFERROR(VLOOKUP(E32,'[11]SAP Input-BS'!$A$5:$E$500,5,0),0) -> -1.4897683e+08 | L32: -1.2064413e+09
A33: Current liabilities ( ≤ 1 year) | B33: Financial liabilities ≤ 1 y | D33: Liabilities PTA/dividends - K | E33: 21321 | F33: =IFERROR(VLOOKUP(E33,'[9]SAP Input-BS'!$A$5:$F$502,5,0),0) -> 0 | G33: =IFERROR(VLOOKUP(E33,'[10]SAP Input-BS'!$A$5:$F$500,5,0),0) -> 0 | H33: =F33-G33 -> 0 | K33: =IFERROR(VLOOKUP(E33,'[11]SAP Input-BS'!$A$5:$E$500,5,0),0) -> 0 | L33: 0
A34: Current liabilities ( ≤ 1 year) | B34: Financial liabilities ≤ 1 y | C34: Debtors with Credit balance | D34: Debtors with credit balances - K | E34: 21324 | F34: =IFERROR(VLOOKUP(E34,'[9]SAP Input-BS'!$A$5:$F$502,5,0),0) -> -13800179 | G34: =IFERROR(VLOOKUP(E34,'[10]SAP Input-BS'!$A$5:$F$500,5,0),0) -> -29669370 | H34: =F34-G34 -> 15869191 | K34: =IFERROR(VLOOKUP(E34,'[11]SAP Input-BS'!$A$5:$E$500,5,0),0) -> -37223401 | L34: -8816775.8
A35: Current liabilities ( ≤ 1 year) | B35: Financial liabilities ≤ 1 y | D35: Liabilities accrued interest - K | E35: 21325 | F35: =IFERROR(VLOOKUP(E35,'[9]SAP Input-BS'!$A$5:$F$502,5,0),0) -> 0 | G35: =IFERROR(VLOOKUP(E35,'[10]SAP Input-BS'!$A$5:$F$500,5,0),0) -> 0 | H35: =F35-G35 -> 0 | K35: =IFERROR(VLOOKUP(E35,'[11]SAP Input-BS'!$A$5:$E$500,5,0),0) -> 0 | L35: 0
A36: Current liabilities ( ≤ 1 year) | B36: Financial liabilities ≤ 1 y | D36: Other financial liabilities ≤ 1 y - K | E36: 21328 | F36: =IFERROR(VLOOKUP(E36,'[9]SAP Input-BS'!$A$5:$F$502,5,0),0) -> -17855875 | G36: =IFERROR(VLOOKUP(E36,'[10]SAP Input-BS'!$A$5:$F$500,5,0),0) -> 0 | H36: =F36-G36 -> -17855875 | K36: =IFERROR(VLOOKUP(E36,'[11]SAP Input-BS'!$A$5:$E$500,5,0),0) -> 0 | L36: 0
A37: Current liabilities ( ≤ 1 year) | B37: Financial liabilities ≤ 1 y | D37: Liabilities PTA/dividends - N | E37: 21341 | F37: =IFERROR(VLOOKUP(E37,'[9]SAP Input-BS'!$A$5:$F$502,5,0),0) -> 0 | G37: =IFERROR(VLOOKUP(E37,'[10]SAP Input-BS'!$A$5:$F$500,5,0),0) -> 0 | H37: =F37-G37 -> 0 | K37: =IFERROR(VLOOKUP(E37,'[11]SAP Input-BS'!$A$5:$E$500,5,0),0) -> 0 | L37: 0
A38: Current liabilities ( ≤ 1 year) | B38: Financial liabilities ≤ 1 y | D38: Debtors with credit balances - N | E38: 21344 | F38: =IFERROR(VLOOKUP(E38,'[9]SAP Input-BS'!$A$5:$F$502,5,0),0) -> 0 | G38: =IFERROR(VLOOKUP(E38,'[10]SAP Input-BS'!$A$5:$F$500,5,0),0) -> 0 | H38: =F38-G38 -> 0 | K38: =IFERROR(VLOOKUP(E38,'[11]SAP Input-BS'!$A$5:$E$500,5,0),0) -> 0 | L38: 0
A39: Current liabilities ( ≤ 1 year) | B39: Financial liabilities ≤ 1 y | D39: Liabilities accrued interest - N | E39: 21345 | F39: =IFERROR(VLOOKUP(E39,'[9]SAP Input-BS'!$A$5:$F$502,5,0),0) -> 0 | G39: =IFERROR(VLOOKUP(E39,'[10]SAP Input-BS'!$A$5:$F$500,5,0),0) -> 0 | H39: =F39-G39 -> 0 | K39: =IFERROR(VLOOKUP(E39,'[11]SAP Input-BS'!$A$5:$E$500,5,0),0) -> 0 | L39: 0
A40: Current liabilities ( ≤ 1 year) | B40: Financial liabilities ≤ 1 y | D40: Other financial liabilities ≤ 1 y - N | E40: 21348 | F40: =IFERROR(VLOOKUP(E40,'[9]SAP Input-BS'!$A$5:$F$502,5,0),0) -> 0 | G40: =IFERROR(VLOOKUP(E40,'[10]SAP Input-BS'!$A$5:$F$500,5,0),0) -> 0 | H40: =F40-G40 -> 0 | K40: =IFERROR(VLOOKUP(E40,'[11]SAP Input-BS'!$A$5:$E$500,5,0),0) -> 0 | L40: 0
A41: Current liabilities ( ≤ 1 year) | B41: Financial liabilities ≤ 1 y | D41: Liabilities dividends - B-a | E41: 21361 | F41: =IFERROR(VLOOKUP(E41,'[9]SAP Input-BS'!$A$5:$F$502,5,0),0) -> 0 | G41: =IFERROR(VLOOKUP(E41,'[10]SAP Input-BS'!$A$5:$F$500,5,0),0) -> 0 | H41: =F41-G41 -> 0 | K41: =IFERROR(VLOOKUP(E41,'[11]SAP Input-BS'!$A$5:$E$500,5,0),0) -> 0 | L41: 0
A42: Current liabilities ( ≤ 1 year) | B42: Financial liabilities ≤ 1 y | D42: Debtors with credit balances - B-a | E42: 21364 | F42: =IFERROR(VLOOKUP(E42,'[9]SAP Input-BS'!$A$5:$F$502,5,0),0) -> 0 | G42: =IFERROR(VLOOKUP(E42,'[10]SAP Input-BS'!$A$5:$F$500,5,0),0) -> 0 | H42: =F42-G42 -> 0 | K42: =IFERROR(VLOOKUP(E42,'[11]SAP Input-BS'!$A$5:$E$500,5,0),0) -> 0 | L42: 0
A43: Current liabilities ( ≤ 1 year) | B43: Financial liabilities ≤ 1 y | D43: Liabilities accrued interest - B-a | E43: 21365 | F43: =IFERROR(VLOOKUP(E43,'[9]SAP Input-BS'!$A$5:$F$502,5,0),0) -> 0 | G43: =IFERROR(VLOOKUP(E43,'[10]SAP Input-BS'!$A$5:$F$500,5,0),0) -> 0 | H43: =F43-G43 -> 0 | K43: =IFERROR(VLOOKUP(E43,'[11]SAP Input-BS'!$A$5:$E$500,5,0),0) -> 0 | L43: 0
A44: Current liabilities ( ≤ 1 year) | B44: Financial liabilities ≤ 1 y | D44: Other financial liabilities ≤ 1 y - B-a | E44: 21368 | F44: =IFERROR(VLOOKUP(E44,'[9]SAP Input-BS'!$A$5:$F$502,5,0),0) -> 0 | G44: =IFERROR(VLOOKUP(E44,'[10]SAP Input-BS'!$A$5:$F$500,5,0),0) -> 0 | H44: =F44-G44 -> 0 | K44: =IFERROR(VLOOKUP(E44,'[11]SAP Input-BS'!$A$5:$E$500,5,0),0) -> 0 | L44: 0
A45: Current liabilities ( ≤ 1 year) | B45: Financial liabilities ≤ 1 y | C45: JKL Provision and Salary Payable | D45: Financial liabil. to board members, employees ≤ 1 y | E45: 21391 | F45: =IFERROR(VLOOKUP(E45,'[9]SAP Input-BS'!$A$5:$F$502,5,0),0) -> -1.8464235e+08 | G45: =IFERROR(VLOOKUP(E45,'[10]SAP Input-BS'!$A$5:$F$500,5,0),0) -> -1.5547929e+09 | H45: =F45-G45 -> 1.3701505e+09 | J45: =(F45-G45)/87 -> 15748857 | K45: =IFERROR(VLOOKUP(E45,'[11]SAP Input-BS'!$A$5:$E$500,5,0),0) -> 4.3246289e+08 | L45: 1.0278321e+08
A46: Current liabilities ( ≤ 1 year) | B46: Financial liabilities ≤ 1 y | D46: Total: Financial liabilities ≤ 1 y | E46: LC_FL | F46: =IFERROR(VLOOKUP(E46,'[9]SAP Input-BS'!$A$5:$F$502,5,0),0) -> -1.5534833e+09 | G46: =IFERROR(VLOOKUP(E46,'[10]SAP Input-BS'!$A$5:$F$500,5,0),0) -> -3.4290619e+09 | H46: =F46-G46 -> 1.8755786e+09 | K46: =IFERROR(VLOOKUP(E46,'[11]SAP Input-BS'!$A$5:$E$500,5,0),0) -> -4.9290017e+08 | L46: -1.6785808e+09
A47: Current liabilities ( ≤ 1 year) | B47: Contract liabilities (CL) ≤ 1 y | D47: CL: Sales over time ≤ 1 y - 3rd, N, B-a, B-c, B-f | E47: 20200 | F47: =IFERROR(VLOOKUP(E47,'[9]SAP Input-BS'!$A$5:$F$502,5,0),0) -> -1.6835769e+08 | G47: =IFERROR(VLOOKUP(E47,'[10]SAP Input-BS'!$A$5:$F$500,5,0),0) -> -1.899379e+08 | H47: =F47-G47 -> 21580209 | K47: =IFERROR(VLOOKUP(E47,'[11]SAP Input-BS'!$A$5:$E$500,5,0),0) -> -279536657 | L47: -1.8909349e+08
A48: Current liabilities ( ≤ 1 year) | B48: Contract liabilities (CL) ≤ 1 y | D48: CL: Prepayments received R&D ≤ 1 y - 3rd, N, B-a, B-c, B-f | E48: 20203 | F48: =IFERROR(VLOOKUP(E48,'[9]SAP Input-BS'!$A$5:$F$502,5,0),0) -> 0 | G48: =IFERROR(VLOOKUP(E48,'[10]SAP Input-BS'!$A$5:$F$500,5,0),0) -> 0 | H48: =F48-G48 -> 0 | K48: =IFERROR(VLOOKUP(E48,'[11]SAP Input-BS'!$A$5:$E$500,5,0),0) -> 0 | L48: 0
A49: Current liabilities ( ≤ 1 year) | B49: Contract liabilities (CL) ≤ 1 y | D49: CL: Prepayments received ≤ 1 y - 3rd, N, B-a, B-c, B-f | E49: 20210 | F49: =IFERROR(VLOOKUP(E49,'[9]SAP Input-BS'!$A$5:$F$502,5,0),0) -> -31594787 | G49: =IFERROR(VLOOKUP(E49,'[10]SAP Input-BS'!$A$5:$F$500,5,0),0) -> -43316145 | H49: =F49-G49 -> 11721359 | K49: =IFERROR(VLOOKUP(E49,'[11]SAP Input-BS'!$A$5:$E$500,5,0),0) -> -5.2535746e+08 | L49: -5.0816196e+08
A50: Current liabilities ( ≤ 1 year) | B50: Contract liabilities (CL) ≤ 1 y | D50: CL: Sales over time ≤ 1 y – K | E50: 20215 | F50: =IFERROR(VLOOKUP(E50,'[9]SAP Input-BS'!$A$5:$F$502,5,0),0) -> 0 | G50: =IFERROR(VLOOKUP(E50,'[10]SAP Input-BS'!$A$5:$F$500,5,0),0) -> 0 | H50: =F50-G50 -> 0 | K50: =IFERROR(VLOOKUP(E50,'[11]SAP Input-BS'!$A$5:$E$500,5,0),0) -> 0 | L50: 0
A51: Current liabilities ( ≤ 1 year) | B51: Contract liabilities (CL) ≤ 1 y | D51: CL: Prepayments received ≤ 1 y - K | E51: 20220 | F51: =IFERROR(VLOOKUP(E51,'[9]SAP Input-BS'!$A$5:$F$502,5,0),0) -> -1886953.9 | G51: =IFERROR(VLOOKUP(E51,'[10]SAP Input-BS'!$A$5:$F$500,5,0),0) -> -42398465 | H51: =F51-G51 -> 40511511 | K51: =IFERROR(VLOOKUP(E51,'[11]SAP Input-BS'!$A$5:$E$500,5,0),0) -> -1886953.9 | L51: -46465754
A52: Current liabilities ( ≤ 1 year) | B52: Contract liabilities (CL) ≤ 1 y | D52: CL: other sales rel. def. Inc. ≤ 1 y - 3rd, N, B-a, B-c, B-f | E52: 20250 | F52: =IFERROR(VLOOKUP(E52,'[9]SAP Input-BS'!$A$5:$F$502,5,0),0) -> 0 | G52: =IFERROR(VLOOKUP(E52,'[10]SAP Input-BS'!$A$5:$F$500,5,0),0) -> 0 | H52: =F52-G52 -> 0 | K52: =IFERROR(VLOOKUP(E52,'[11]SAP Input-BS'!$A$5:$E$500,5,0),0) -> 0 | L52: 0
A53: Current liabilities ( ≤ 1 year) | B53: Contract liabilities (CL) ≤ 1 y | D53: CL: other sales related deferred income ≤ 1 y - K | E53: 20251 | F53: =IFERROR(VLOOKUP(E53,'[9]SAP Input-BS'!$A$5:$F$502,5,0),0) -> 0 | G53: =IFERROR(VLOOKUP(E53,'[10]SAP Input-BS'!$A$5:$F$500,5,0),0) -> 0 | H53: =F53-G53 -> 0 | K53: =IFERROR(VLOOKUP(E53,'[11]SAP Input-BS'!$A$5:$E$500,5,0),0) -> 0 | L53: 0
A54: Current liabilities ( ≤ 1 year) | B54: Contract liabilities (CL) ≤ 1 y | D54: CL: deferral received tooling grants ≤ 1 y | E54: 20255 | F54: =IFERROR(VLOOKUP(E54,'[9]SAP Input-BS'!$A$5:$F$502,5,0),0) -> 0 | G54: =IFERROR(VLOOKUP(E54,'[10]SAP Input-BS'!$A$5:$F$500,5,0),0) -> 0 | H54: =F54-G54 -> 0 | K54: =IFERROR(VLOOKUP(E54,'[11]SAP Input-BS'!$A$5:$E$500,5,0),0) -> 0 | L54: 0
A55: Current liabilities ( ≤ 1 year) | B55: Contract liabilities (CL) ≤ 1 y | D55: Total: Contract liabilities (CL) ≤ 1 y | E55: LC_CL | F55: =IFERROR(VLOOKUP(E55,'[9]SAP Input-BS'!$A$5:$F$502,5,0),0) -> -2.0183943e+08 | G55: =IFERROR(VLOOKUP(E55,'[10]SAP Input-BS'!$A$5:$F$500,5,0),0) -> -2.7565251e+08 | H55: =F55-G55 -> 73813078 | K55: =IFERROR(VLOOKUP(E55,'[11]SAP Input-BS'!$A$5:$E$500,5,0),0) -> -8.0678107e+08 | L55: -7.4372121e+08
A56: Current liabilities ( ≤ 1 year) | B56: Income tax liabilities ≤ 1 y | D56: Income tax liabilities | E56: 21200 | F56: =IFERROR(VLOOKUP(E56,'[9]SAP Input-BS'!$A$5:$F$502,5,0),0) -> 0 | G56: =IFERROR(VLOOKUP(E56,'[10]SAP Input-BS'!$A$5:$F$500,5,0),0) -> 0.39 | H56: =F56-G56 -> -0.39 | K56: =IFERROR(VLOOKUP(E56,'[11]SAP Input-BS'!$A$5:$E$500,5,0),0) -> 0.39 | L56: 0.39
A57: Current liabilities ( ≤ 1 year) | B57: Income tax liabilities ≤ 1 y | D57: Total: Income tax liabilities ≤ 1 y | E57: LC_IT | F57: =IFERROR(VLOOKUP(E57,'[9]SAP Input-BS'!$A$5:$F$502,5,0),0) -> 0 | G57: =IFERROR(VLOOKUP(E57,'[10]SAP Input-BS'!$A$5:$F$500,5,0),0) -> 0.39 | H57: =F57-G57 -> -0.39 | K57: =IFERROR(VLOOKUP(E57,'[11]SAP Input-BS'!$A$5:$E$500,5,0),0) -> 0.39 | L57: 0.39
... A98: Current liabilities ( ≤ 1 year) | B98: Current provisions | D98: Sales related provisions ≤ 1 y | E98: 23339 | F98: =IFERROR(VLOOKUP(E98,'[9]SAP Input-BS'!$A$5:$F$502,5,0),0) -> -48213234 | G98: =IFERROR(VLOOKUP(E98,'[10]SAP Input-BS'!$A$5:$F$500,5,0),0) -> -49228809 | H98: =F98-G98 -> 1015575 | K98: =IFERROR(VLOOKUP(E98,'[11]SAP Input-BS'!$A$5:$E$500,5,0),0) -> -80022777 | L98: -53750618
A99: Current liabilities ( ≤ 1 year) | B99: Current provisions | D99: Sundry other provisions ≤ 1 y | E99: 23369 | F99: =IFERROR(VLOOKUP(E99,'[9]SAP Input-BS'!$A$5:$F$502,5,0),0) -> -2182256364 | G99: =IFERROR(VLOOKUP(E99,'[10]SAP Input-BS'!$A$5:$F$500,5,0),0) -> -1774763788 | H99: =F99-G99 -> -407492576 | J99: Tax Provisions | K99: =IFERROR(VLOOKUP(E99,'[11]SAP Input-BS'!$A$5:$E$500,5,0),0) -> -1903136172 | L99: -1781933553
A100: Current liabilities ( ≤ 1 year) | B100: Current provisions | D100: Total: Current provisions | E100: LC_PR | F100: =IFERROR(VLOOKUP(E100,'[9]SAP Input-BS'!$A$5:$F$502,5,0),0) -> -4671531768 | G100: =IFERROR(VLOOKUP(E100,'[10]SAP Input-BS'!$A$5:$F$500,5,0),0) -> -4.2242548e+09 | H100: =F100-G100 -> -4.4727695e+08 | K100: =IFERROR(VLOOKUP(E100,'[11]SAP Input-BS'!$A$5:$E$500,5,0),0) -> -6.3441198e+09 | L100: -6.5843411e+09
A101: Current liabilities ( ≤ 1 year) | B101: Total: Current liabilities | C101: Total: Current liabilities | D101: Total: Current liabilities | E101: LC_TO | F101: =IFERROR(VLOOKUP(E101,'[9]SAP Input-BS'!$A$5:$F$502,5,0),0) -> -2.6383189e+10 | G101: =IFERROR(VLOOKUP(E101,'[10]SAP Input-BS'!$A$5:$F$500,5,0),0) -> -2.7857044e+10 | H101: =F101-G101 -> 1.4738552e+09 | K101: =IFERROR(VLOOKUP(E101,'[11]SAP Input-BS'!$A$5:$E$500,5,0),0) -> -2.6067301e+10 | L101: -3.5635505e+10
H102: =F102-G102 -> 0
A103: Non-current liabilities ( > 1 year) | B103: Financial liabilities > 1 y | D103: Bonds > 1 y | E103: 24010 | F103: =IFERROR(VLOOKUP(E103,'[9]SAP Input-BS'!$A$5:$F$502,5,0),0) -> 0 | G103: =IFERROR(VLOOKUP(E103,'[10]SAP Input-BS'!$A$5:$F$500,5,0),0) -> 0 | H103: =F103-G103 -> 0 | K103: =IFERROR(VLOOKUP(E103,'[11]SAP Input-BS'!$A$5:$E$500,5,0),0) -> 0 | L103: 0
A104: Non-current liabilities ( > 1 year) | B104: Financial liabilities > 1 y | D104: Liabilities with banks > 1 y | E104: 24020 | F104: =IFERROR(VLOOKUP(E104,'[9]SAP Input-BS'!$A$5:$F$502,5,0),0) -> 0 | G104: =IFERROR(VLOOKUP(E104,'[10]SAP Input-BS'!$A$5:$F$500,5,0),0) -> 0 | H104: =F104-G104 -> 0 | K104: =IFERROR(VLOOKUP(E104,'[11]SAP Input-BS'!$A$5:$E$500,5,0),0) -> 0 | L104: 0
A105: Non-current liabilities ( > 1 year) | B105: Financial liabilities > 1 y | D105: Commercial papers > 1 y | E105: 24030 | F105: =IFERROR(VLOOKUP(E105,'[9]SAP Input-BS'!$A$5:$F$502,5,0),0) -> 0 | G105: =IFERROR(VLOOKUP(E105,'[10]SAP Input-BS'!$A$5:$F$500,5,0),0) -> 0 | H105: =F105-G105 -> 0 | K105: =IFERROR(VLOOKUP(E105,'[11]SAP Input-BS'!$A$5:$E$500,5,0),0) -> 0 | L105: 0
A106: Non-current liabilities ( > 1 year) | B106: Financial liabilities > 1 y | D106: Promissory note loan > 1 y | E106: 24035 | F106: =IFERROR(VLOOKUP(E106,'[9]SAP Input-BS'!$A$5:$F$502,5,0),0) -> 0 | G106: =IFERROR(VLOOKUP(E106,'[10]SAP Input-BS'!$A$5:$F$500,5,0),0) -> 0 | H106: =F106-G106 -> 0 | K106: =IFERROR(VLOOKUP(E106,'[11]SAP Input-BS'!$A$5:$E$500,5,0),0) -> 0 | L106: 0
A107: Non-current liabilities ( > 1 year) | B107: Financial liabilities > 1 y | D107: Other financial liabilities > 1 y | E107: 24040 | F107: =IFERROR(VLOOKUP(E107,'[9]SAP Input-BS'!$A$5:$F$502,5,0),0) -> 0 | G107: =IFERROR(VLOOKUP(E107,'[10]SAP Input-BS'!$A$5:$F$500,5,0),0) -> 0 | H107: =F107-G107 -> 0 | K107: =IFERROR(VLOOKUP(E107,'[11]SAP Input-BS'!$A$5:$E$500,5,0),0) -> 0 | L107: 0
A108: Non-current liabilities ( > 1 year) | B108: Financial liabilities > 1 y | D108: Total: Financial liabilities > 1 y | E108: 24049 | F108: =IFERROR(VLOOKUP(E108,'[9]SAP Input-BS'!$A$5:$F$502,5,0),0) -> 0 | G108: =IFERROR(VLOOKUP(E108,'[10]SAP Input-BS'!$A$5:$F$500,5,0),0) -> 0 | H108: =F108-G108 -> 0 | K108: =IFERROR(VLOOKUP(E108,'[11]SAP Input-BS'!$A$5:$E$500,5,0),0) -> 0 | L108: 0
A109: Non-current liabilities ( > 1 year) | B109: Loans | D109: Loans > 1 y - 3rd, B-c, B-f | E109: 24100 | F109: =IFERROR(VLOOKUP(E109,'[9]SAP Input-BS'!$A$5:$F$502,5,0),0) -> 0 | G109: =IFERROR(VLOOKUP(E109,'[10]SAP Input-BS'!$A$5:$F$500,5,0),0) -> 0 | H109: =F109-G109 -> 0 | K109: =IFERROR(VLOOKUP(E109,'[11]SAP Input-BS'!$A$5:$E$500,5,0),0) -> 0 | L109: 0
A110: Non-current liabilities ( > 1 year) | B110: Loans | D110: Loans > 1 y - K | E110: 24120 | F110: =IFERROR(VLOOKUP(E110,'[9]SAP Input-BS'!$A$5:$F$502,5,0),0) -> 0 | G110: =IFERROR(VLOOKUP(E110,'[10]SAP Input-BS'!$A$5:$F$500,5,0),0) -> 0 | H110: =F110-G110 -> 0 | K110: =IFERROR(VLOOKUP(E110,'[11]SAP Input-BS'!$A$5:$E$500,5,0),0) -> 0 | L110: 0
A111: Non-current liabilities ( > 1 year) | B111: Loans | D111: Loans > 1 y - N | E111: 24140 | F111: =IFERROR(VLOOKUP(E111,'[9]SAP Input-BS'!$A$5:$F$502,5,0),0) -> 0 | G111: =IFERROR(VLOOKUP(E111,'[10]SAP Input-BS'!$A$5:$F$500,5,0),0) -> 0 | H111: =F111-G111 -> 0 | K111: =IFERROR(VLOOKUP(E111,'[11]SAP Input-BS'!$A$5:$E$500,5,0),0) -> 0 | L111: 0
A112: Non-current liabilities ( > 1 year) | B112: Loans | D112: Loans > 1 y - B-a | E112: 24160 | F112: =IFERROR(VLOOKUP(E112,'[9]SAP Input-BS'!$A$5:$F$502,5,0),0) -> 0 | G112: =IFERROR(VLOOKUP(E112,'[10]SAP Input-BS'!$A$5:$F$500,5,0),0) -> 0 | H112: =F112-G112 -> 0 | K112: =IFERROR(VLOOKUP(E112,'[11]SAP Input-BS'!$A$5:$E$500,5,0),0) -> 0 | L112: 0
A113: Non-current liabilities ( > 1 year) | B113: Loans | D113: Total: Loans > 1 y | E113: 24189 | F113: =IFERROR(VLOOKUP(E113,'[9]SAP Input-BS'!$A$5:$F$502,5,0),0) -> 0 | G113: =IFERROR(VLOOKUP(E113,'[10]SAP Input-BS'!$A$5:$F$500,5,0),0) -> 0 | H113: =F113-G113 -> 0 | K113: =IFERROR(VLOOKUP(E113,'[11]SAP Input-BS'!$A$5:$E$500,5,0),0) -> 0 | L113: 0
A114: Non-current liabilities ( > 1 year) | B114: Financial Liabilities > 1 y | D114: Derivatives w/o hedge > 1y - 3rd | E114: 24205 | F114: =IFERROR(VLOOKUP(E114,'[9]SAP Input-BS'!$A$5:$F$502,5,0),0) -> 0 | G114: =IFERROR(VLOOKUP(E114,'[10]SAP Input-BS'!$A$5:$F$500,5,0),0) -> 0 | H114: =F114-G114 -> 0 | K114: =IFERROR(VLOOKUP(E114,'[11]SAP Input-BS'!$A$5:$E$500,5,0),0) -> 0 | L114: 0
... A120: Non-current liabilities ( > 1 year) | B120: Financial Liabilities > 1 y | D120: Total: Financial Liabilities > 1 y | E120: LN_FL | F120: =IFERROR(VLOOKUP(E120,'[9]SAP Input-BS'!$A$5:$F$502,5,0),0) -> 0 | G120: =IFERROR(VLOOKUP(E120,'[10]SAP Input-BS'!$A$5:$F$500,5,0),0) -> 0 | H120: =F120-G120 -> 0 | K120: =IFERROR(VLOOKUP(E120,'[11]SAP Input-BS'!$A$5:$E$500,5,0),0) -> 0 | L120: 0
A121: Non-current liabilities ( > 1 year) | B121: Lease liabilities (lessee) > 1 y | C121: Lease liabilities (lessee) > 1 y | D121: Lease liabilities (lessee) > 1 y | E121: 24500 | F121: =IFERROR(VLOOKUP(E121,'[9]SAP Input-BS'!$A$5:$F$502,5,0),0) -> -7.7802269e+09 | G121: =IFERROR(VLOOKUP(E121,'[10]SAP Input-BS'!$A$5:$F$500,5,0),0) -> -7.4046773e+09 | H121: =F121-G121 -> -3.7554964e+08 | K121: =IFERROR(VLOOKUP(E121,'[11]SAP Input-BS'!$A$5:$E$500,5,0),0) -> -8282791658 | L121: -7.7033103e+09
A122: Non-current liabilities ( > 1 year) | B122: Lease liabilities (lessee) > 1 y | C122: Lease liabilities (lessee) > 1 y | D122: Total: Lease liabilities (lessee) > 1 y | E122: LN_LL | F122: =IFERROR(VLOOKUP(E122,'[9]SAP Input-BS'!$A$5:$F$502,5,0),0) -> -7.7802269e+09 | G122: =IFERROR(VLOOKUP(E122,'[10]SAP Input-BS'!$A$5:$F$500,5,0),0) -> -7.4046773e+09 | H122: =F122-G122 -> -3.7554964e+08 | K122: =IFERROR(VLOOKUP(E122,'[11]SAP Input-BS'!$A$5:$E$500,5,0),0) -> -8282791658 | L122: -7.7033103e+09
A123: Non-current liabilities ( > 1 year) | B123: Contract liabilities > 1 y | D123: CL: Sales over time > 1 y - 3rd, N, B-a, B-c, B-f | E123: 25000 | F123: =IFERROR(VLOOKUP(E123,'[9]SAP Input-BS'!$A$5:$F$502,5,0),0) -> -459175924 | G123: =IFERROR(VLOOKUP(E123,'[10]SAP Input-BS'!$A$5:$F$500,5,0),0) -> -461625454 | H123: =F123-G123 -> 2449530 | K123: =IFERROR(VLOOKUP(E123,'[11]SAP Input-BS'!$A$5:$E$500,5,0),0) -> 0 | L123: 0
A124: Non-current liabilities ( > 1 year) | B124: Contract liabilities > 1 y | D124: CL: Prepayments received R&D > 1 y - 3rd, N, B-a, B-c, B-f | E124: 25003 | F124: =IFERROR(VLOOKUP(E124,'[9]SAP Input-BS'!$A$5:$F$502,5,0),0) -> 0 | G124: =IFERROR(VLOOKUP(E124,'[10]SAP Input-BS'!$A$5:$F$500,5,0),0) -> 0 | H124: =F124-G124 -> 0 | K124: =IFERROR(VLOOKUP(E124,'[11]SAP Input-BS'!$A$5:$E$500,5,0),0) -> 0 | L124: 0
A125: Non-current liabilities ( > 1 year) | B125: Contract liabilities > 1 y | D125: CL: Prepayments received > 1 y - 3rd, N, B-a, B-c, B-f | E125: 25011 | F125: =IFERROR(VLOOKUP(E125,'[9]SAP Input-BS'!$A$5:$F$502,5,0),0) -> 0 | G125: =IFERROR(VLOOKUP(E125,'[10]SAP Input-BS'!$A$5:$F$500,5,0),0) -> 0 | H125: =F125-G125 -> 0 | K125: =IFERROR(VLOOKUP(E125,'[11]SAP Input-BS'!$A$5:$E$500,5,0),0) -> 0 | L125: 0
A126: Non-current liabilities ( > 1 year) | B126: Contract liabilities > 1 y | D126: CL: Sales over time > 1 y – K | E126: 25015 | F126: =IFERROR(VLOOKUP(E126,'[9]SAP Input-BS'!$A$5:$F$502,5,0),0) -> 0 | G126: =IFERROR(VLOOKUP(E126,'[10]SAP Input-BS'!$A$5:$F$500,5,0),0) -> 0 | H126: =F126-G126 -> 0 | K126: =IFERROR(VLOOKUP(E126,'[11]SAP Input-BS'!$A$5:$E$500,5,0),0) -> 0 | L126: 0
A127: Non-current liabilities ( > 1 year) | B127: Contract liabilities > 1 y | D127: CL: Prepayments received > 1 y - K | E127: 25020 | F127: =IFERROR(VLOOKUP(E127,'[9]SAP Input-BS'!$A$5:$F$502,5,0),0) -> 0 | G127: =IFERROR(VLOOKUP(E127,'[10]SAP Input-BS'!$A$5:$F$500,5,0),0) -> 0 | H127: =F127-G127 -> 0 | K127: =IFERROR(VLOOKUP(E127,'[11]SAP Input-BS'!$A$5:$E$500,5,0),0) -> 0 | L127: 0
A128: Non-current liabilities ( > 1 year) | B128: Contract liabilities > 1 y | D128: CL: other sales rel. def. Inc. > 1 y - 3rd, N, B-a, B-c, B-f | E128: 25050 | F128: =IFERROR(VLOOKUP(E128,'[9]SAP Input-BS'!$A$5:$F$502,5,0),0) -> 0 | G128: =IFERROR(VLOOKUP(E128,'[10]SAP Input-BS'!$A$5:$F$500,5,0),0) -> 0 | H128: =F128-G128 -> 0 | K128: =IFERROR(VLOOKUP(E128,'[11]SAP Input-BS'!$A$5:$E$500,5,0),0) -> 0 | L128: 0
A129: Non-current liabilities ( > 1 year) | B129: Contract liabilities > 1 y | D129: CL: other sales related deferred income > 1 y - K | E129: 25051 | F129: =IFERROR(VLOOKUP(E129,'[9]SAP Input-BS'!$A$5:$F$502,5,0),0) -> 0 | G129: =IFERROR(VLOOKUP(E129,'[10]SAP Input-BS'!$A$5:$F$500,5,0),0) -> 0 | H129: =F129-G129 -> 0 | K129: =IFERROR(VLOOKUP(E129,'[11]SAP Input-BS'!$A$5:$E$500,5,0),0) -> 0 | L129: 0
A130: Non-current liabilities ( > 1 year) | B130: Contract liabilities > 1 y | D130: CL: Deferral received tooling grants > 1 y | E130: 25055 | F130: =IFERROR(VLOOKUP(E130,'[9]SAP Input-BS'!$A$5:$F$502,5,0),0) -> 0 | G130: =IFERROR(VLOOKUP(E130,'[10]SAP Input-BS'!$A$5:$F$500,5,0),0) -> 0 | H130: =F130-G130 -> 0 | K130: =IFERROR(VLOOKUP(E130,'[11]SAP Input-BS'!$A$5:$E$500,5,0),0) -> 0 | L130: 0
A131: Non-current liabilities ( > 1 year) | B131: Contract liabilities > 1 y | D131: Total: Contract liabilities > 1 y | E131: LN_CL | F131: =IFERROR(VLOOKUP(E131,'[9]SAP Input-BS'!$A$5:$F$502,5,0),0) -> -459175924 | G131: =IFERROR(VLOOKUP(E131,'[10]SAP Input-BS'!$A$5:$F$500,5,0),0) -> -461625454 | H131: =F131-G131 -> 2449530 | K131: =IFERROR(VLOOKUP(E131,'[11]SAP Input-BS'!$A$5:$E$500,5,0),0) -> 0 | L131: 0
A132: Non-current liabilities ( > 1 year) | B132: Other Liabilities > 1 y | D132: Other sundry liabil. > 1 y - 3rd, B-c, B-f | E132: 24300 | F132: =IFERROR(VLOOKUP(E132,'[9]SAP Input-BS'!$A$5:$F$502,5,0),0) -> 0 | G132: =IFERROR(VLOOKUP(E132,'[10]SAP Input-BS'!$A$5:$F$500,5,0),0) -> 0 | H132: =F132-G132 -> 0 | K132: =IFERROR(VLOOKUP(E132,'[11]SAP Input-BS'!$A$5:$E$500,5,0),0) -> 0 | L132: 0
A133: Non-current liabilities ( > 1 year) | B133: Other Liabilities > 1 y | D133: Other sundry liabilities > 1 y - K | E133: 24320 | F133: =IFERROR(VLOOKUP(E133,'[9]SAP Input-BS'!$A$5:$F$502,5,0),0) -> 0 | G133: =IFERROR(VLOOKUP(E133,'[10]SAP Input-BS'!$A$5:$F$500,5,0),0) -> 0 | H133: =F133-G133 -> 0 | K133: =IFERROR(VLOOKUP(E133,'[11]SAP Input-BS'!$A$5:$E$500,5,0),0) -> 0 | L133: 0
A134: Non-current liabilities ( > 1 year) | B134: Other Liabilities > 1 y | D134: Other sundry liabilities > 1 y - N | E134: 24340 | F134: =IFERROR(VLOOKUP(E134,'[9]SAP Input-BS'!$A$5:$F$502,5,0),0) -> 0 | G134: =IFERROR(VLOOKUP(E134,'[10]SAP Input-BS'!$A$5:$F$500,5,0),0) -> 0 | H134: =F134-G134 -> 0 | K134: =IFERROR(VLOOKUP(E134,'[11]SAP Input-BS'!$A$5:$E$500,5,0),0) -> 0 | L134: 0
... A153: Non-current liabilities ( > 1 year) | B153: Deferred tax liabilities | D153: Total: Deferred tax liabilities | E153: LN_DT | F153: =IFERROR(VLOOKUP(E153,'[9]SAP Input-BS'!$A$5:$F$502,5,0),0) -> 0 | G153: =IFERROR(VLOOKUP(E153,'[10]SAP Input-BS'!$A$5:$F$500,5,0),0) -> 0 | H153: =F153-G153 -> 0 | K153: =IFERROR(VLOOKUP(E153,'[11]SAP Input-BS'!$A$5:$E$500,5,0),0) -> 0 | L153: 0
A154: Non-current liabilities ( > 1 year) | B154: Non-current liabilities | C154: Non-current liabilities | D154: Total: Non-current liabilities | E154: LN_TO | F154: =IFERROR(VLOOKUP(E154,'[9]SAP Input-BS'!$A$5:$F$502,5,0),0) -> -1.4875909e+10 | G154: =IFERROR(VLOOKUP(E154,'[10]SAP Input-BS'!$A$5:$F$500,5,0),0) -> -1.3093466e+10 | H154: =F154-G154 -> -1.7824426e+09 | K154: =IFERROR(VLOOKUP(E154,'[11]SAP Input-BS'!$A$5:$E$500,5,0),0) -> -2.3523651e+10 | L154: -1.405834e+10
F155: =IFERROR(VLOOKUP(E155,'[9]SAP Input-BS'!$A$5:$F$502,5,0),0) -> 0 | G155: =IFERROR(VLOOKUP(E155,'[10]SAP Input-BS'!$A$5:$F$500,5,0),0) -> 0 | H155: =F155-G155 -> 0 | K155: =IFERROR(VLOOKUP(G155,'[12]SAP Input-BS'!$A$5:$E$500,5,0),0) -> 0 | L155: 0
A156: Equity | B156: Equity | D156: Subscribed Capital | E156: 29000 | F156: =IFERROR(VLOOKUP(E156,'[9]SAP Input-BS'!$A$5:$F$502,5,0),0) -> -41597800 | G156: =IFERROR(VLOOKUP(E156,'[10]SAP Input-BS'!$A$5:$F$500,5,0),0) -> -41597800 | H156: =F156-G156 -> 0 | K156: =IFERROR(VLOOKUP(E156,'[11]SAP Input-BS'!$A$5:$E$500,5,0),0) -> -41597800 | L156: -41597800
A157: Equity | B157: Equity | D157: Capital surplus | E157: 29100 | F157: =IFERROR(VLOOKUP(E157,'[9]SAP Input-BS'!$A$5:$F$502,5,0),0) -> 0 | G157: =IFERROR(VLOOKUP(E157,'[10]SAP Input-BS'!$A$5:$F$500,5,0),0) -> 0 | H157: =F157-G157 -> 0 | K157: =IFERROR(VLOOKUP(E157,'[11]SAP Input-BS'!$A$5:$E$500,5,0),0) -> 0 | L157: 0
A158: Equity | B158: Equity | D158: Total: Earned surplus reserves | E158: 29399 | F158: =IFERROR(VLOOKUP(E158,'[9]SAP Input-BS'!$A$5:$F$502,5,0),0) -> -5.286379e+10 | G158: =IFERROR(VLOOKUP(E158,'[10]SAP Input-BS'!$A$5:$F$500,5,0),0) -> -5.7953582e+10 | H158: =F158-G158 -> 5.0897923e+09 | K158: =IFERROR(VLOOKUP(E158,'[11]SAP Input-BS'!$A$5:$E$500,5,0),0) -> -4.438364e+10 | L158: -5.3566751e+10
A159: Equity | B159: Equity | D159: Unappropriate Earnings/Losses | E159: 29499 | F159: =IFERROR(VLOOKUP(E159,'[9]SAP Input-BS'!$A$5:$F$502,5,0),0) -> 0 | G159: =IFERROR(VLOOKUP(E159,'[10]SAP Input-BS'!$A$5:$F$500,5,0),0) -> 0 | H159: =F159-G159 -> 0 | K159: =IFERROR(VLOOKUP(E159,'[11]SAP Input-BS'!$A$5:$E$500,5,0),0) -> 0 | L159: 0
A160: Equity | B160: Equity | D160: Non-controlling interests | E160: 28800 | F160: =IFERROR(VLOOKUP(E160,'[9]SAP Input-BS'!$A$5:$F$502,5,0),0) -> 0 | G160: =IFERROR(VLOOKUP(E160,'[10]SAP Input-BS'!$A$5:$F$500,5,0),0) -> 0 | H160: =F160-G160 -> 0 | K160: =IFERROR(VLOOKUP(E160,'[11]SAP Input-BS'!$A$5:$E$500,5,0),0) -> 0 | L160: 0
A161: Equity | B161: Equity | D161: Total: Equity | E161: L_EQT | F161: =IFERROR(VLOOKUP(E161,'[9]SAP Input-BS'!$A$5:$F$502,5,0),0) -> -5.2905387e+10 | G161: =IFERROR(VLOOKUP(E161,'[10]SAP Input-BS'!$A$5:$F$500,5,0),0) -> -5.799518e+10 | H161: =F161-G161 -> 5.0897923e+09 | K161: =IFERROR(VLOOKUP(E161,'[11]SAP Input-BS'!$A$5:$E$500,5,0),0) -> -4.4425238e+10 | L161: -5.3608349e+10
F162: =IFERROR(VLOOKUP(E162,'[9]SAP Input-BS'!$A$5:$F$502,5,0),0) -> 0 | G162: =IFERROR(VLOOKUP(E162,'[10]SAP Input-BS'!$A$5:$F$500,5,0),0) -> 0 | H162: =F162-G162 -> 0 | K162: =IFERROR(VLOOKUP(G162,'[12]SAP Input-BS'!$A$5:$E$500,5,0),0) -> 0 | L162: 0
A163: Liabilities and equity | B163: Total: Liabilities and equity | C163: Total: Liabilities and equity | D163: Total: Liabilities and equity | E163: L_TOT | F163: =IFERROR(VLOOKUP(E163,'[9]SAP Input-BS'!$A$5:$F$502,5,0),0)-1 -> -9.4164485e+10 | G163: =IFERROR(VLOOKUP(E163,'[10]SAP Input-BS'!$A$5:$F$500,5,0),0) -> -9.894569e+10 | H163: =F163-G163 -> 4.7812049e+09 | K163: =IFERROR(VLOOKUP(E163,'[11]SAP Input-BS'!$A$5:$E$500,5,0),0) -> -9.4016189e+10 | L163: -1.0330219e+11
...

Sheet BS-Assets
A1: Assets | B1: Main Category | C1: Sub Category | D1: Particulars | E1: Item Number | F1: 46174 | G1: 46082 | H1: Variance | I1: Reasons | K1: 45901 | L1: 45992
A2: Current Assets | B2: Cash and cash equivalents | C2: Cash and cash equivalents | D2: Cheques | E2: 17001 | F2: =IFERROR(VLOOKUP(E2,'[9]SAP Input-BS'!$A$5:$F$502,5,0),0) -> 0 | G2: =IFERROR(VLOOKUP(E2,'[10]SAP Input-BS'!$A$5:$F$500,5,0),0) -> 0 | H2: =F2-G2 -> 0 | K2: =IFERROR(VLOOKUP(E2,'[11]SAP Input-BS'!$A$5:$E$500,5,0),0) -> 0 | L2: 0
A3: Current Assets | B3: Cash and cash equivalents | C3: Cash and cash equivalents | D3: Cash on hand | E3: 17003 | F3: =IFERROR(VLOOKUP(E3,'[9]SAP Input-BS'!$A$5:$F$502,5,0),0) -> 13 | G3: =IFERROR(VLOOKUP(E3,'[10]SAP Input-BS'!$A$5:$F$500,5,0),0) -> 1234 | H3: =F3-G3 -> -1221 | K3: =IFERROR(VLOOKUP(E3,'[11]SAP Input-BS'!$A$5:$E$500,5,0),0) -> 2415 | L3: 2301
A4: Current Assets | B4: Cash and cash equivalents | C4: Cash and cash equivalents | D4: Bank balances ≤ 90 days | E4: 17005 | F4: =IFERROR(VLOOKUP(E4,'[9]SAP Input-BS'!$A$5:$F$502,5,0),0) -> 1.2020967e+10 | G4: =IFERROR(VLOOKUP(E4,'[10]SAP Input-BS'!$A$5:$F$500,5,0),0) -> 1560768050 | H4: =F4-G4 -> 1.0460199e+10 | K4: =IFERROR(VLOOKUP(E4,'[11]SAP Input-BS'!$A$5:$E$500,5,0),0) -> 4.0931609e+09 | L4: 7.5445585e+09
A5: Current Assets | B5: Cash and cash equivalents | C5: Cash and cash equivalents | D5: Total: Cash and cash equivalents | E5: AC_CH | F5: =IFERROR(VLOOKUP(E5,'[9]SAP Input-BS'!$A$5:$F$502,5,0),0) -> 1.2020967e+10 | G5: =IFERROR(VLOOKUP(E5,'[10]SAP Input-BS'!$A$5:$F$500,5,0),0) -> 1560769284 | H5: =F5-G5 -> 1.0460198e+10 | K5: =IFERROR(VLOOKUP(E5,'[11]SAP Input-BS'!$A$5:$E$500,5,0),0) -> 4.0931633e+09 | L5: 7.5445608e+09
A6: Current Assets | B6: Trade receivables | C6: Trade receivables | D6: Trade receivables - 3rd, B-c, B-f | E6: 18000 | F6: =IFERROR(VLOOKUP(E6,'[9]SAP Input-BS'!$A$5:$F$502,5,0),0) -> 1.671417e+09 | G6: =IFERROR(VLOOKUP(E6,'[10]SAP Input-BS'!$A$5:$F$500,5,0),0) -> 2.1105355e+09 | H6: =F6-G6 -> -4.3911846e+08 | K6: =IFERROR(VLOOKUP(E6,'[11]SAP Input-BS'!$A$5:$E$500,5,0),0) -> 2.3140636e+09 | L6: 3.3323581e+09
A7: Current Assets | B7: Trade receivables | C7: Trade receivables | D7: Trade receivables - K | E7: 18020 | F7: =IFERROR(VLOOKUP(E7,'[9]SAP Input-BS'!$A$5:$F$502,5,0),0) -> 1.2685401e+10 | G7: =IFERROR(VLOOKUP(E7,'[10]SAP Input-BS'!$A$5:$F$500,5,0),0) -> 2.1422072e+10 | H7: =F7-G7 -> -8.7366717e+09 | J7: page A.1_K | K7: =IFERROR(VLOOKUP(E7,'[11]SAP Input-BS'!$A$5:$E$500,5,0),0) -> 1.6272224e+10 | L7: 1.5384514e+10
A8: Current Assets | B8: Trade receivables | C8: Trade receivables | D8: License receivables - K | E8: 18025 | F8: =IFERROR(VLOOKUP(E8,'[9]SAP Input-BS'!$A$5:$F$502,5,0),0) -> 0 | G8: =IFERROR(VLOOKUP(E8,'[10]SAP Input-BS'!$A$5:$F$500,5,0),0) -> 0 | H8: =F8-G8 -> 0 | K8: =IFERROR(VLOOKUP(E8,'[11]SAP Input-BS'!$A$5:$E$500,5,0),0) -> 0 | L8: 0
A9: Current Assets | B9: Trade receivables | C9: Trade receivables | D9: Trade receivables - N | E9: 18040 | F9: =IFERROR(VLOOKUP(E9,'[9]SAP Input-BS'!$A$5:$F$502,5,0),0) -> 2.0906083e+08 | G9: =IFERROR(VLOOKUP(E9,'[10]SAP Input-BS'!$A$5:$F$500,5,0),0) -> 2.6702677e+08 | H9: =F9-G9 -> -57965942 | J9: page A.1_N | K9: =IFERROR(VLOOKUP(E9,'[11]SAP Input-BS'!$A$5:$E$500,5,0),0) -> 1.0666313e+08 | L9: 2.5850201e+08
A10: Current Assets | B10: Trade receivables | C10: Trade receivables | D10: Trade receivables - B-a | E10: 18060 | F10: =IFERROR(VLOOKUP(E10,'[9]SAP Input-BS'!$A$5:$F$502,5,0),0) -> 0 | G10: =IFERROR(VLOOKUP(E10,'[10]SAP Input-BS'!$A$5:$F$500,5,0),0) -> 0 | H10: =F10-G10 -> 0 | K10: =IFERROR(VLOOKUP(E10,'[11]SAP Input-BS'!$A$5:$E$500,5,0),0) -> 0 | L10: 0
A11: Current Assets | B11: Trade receivables | C11: Trade receivables | D11: Total: Trade receivables | E11: AC_AR | F11: =IFERROR(VLOOKUP(E11,'[9]SAP Input-BS'!$A$5:$F$502,5,0),0) -> 1.4565878e+10 | G11: =IFERROR(VLOOKUP(E11,'[10]SAP Input-BS'!$A$5:$F$500,5,0),0) -> 2.3799634e+10 | H11: =F11-G11 -> -9.2337561e+09 | K11: =IFERROR(VLOOKUP(E11,'[11]SAP Input-BS'!$A$5:$E$500,5,0),0) -> 1.8692951e+10 | L11: 1.8975374e+10
A12: Current Assets | B12: Other current financial assets | C12: Marketable securities ≤ 1 y. | D12: Money market funds - FVPL | E12: 17057 | F12: =IFERROR(VLOOKUP(E12,'[9]SAP Input-BS'!$A$5:$F$502,5,0),0) -> 11608765263 | G12: =IFERROR(VLOOKUP(E12,'[10]SAP Input-BS'!$A$5:$F$500,5,0),0) -> 14517034946 | H12: =F12-G12 -> -2908269683 | K12: =IFERROR(VLOOKUP(E12,'[11]SAP Input-BS'!$A$5:$E$500,5,0),0) -> 11601775417 | L12: 1.1390965e+10
A13: Current Assets | B13: Other current financial assets | C13: Marketable securities ≤ 1 y. | D13: Marketable securities ≤ 1 y - FVOCI wR | E13: 17066 | F13: =IFERROR(VLOOKUP(E13,'[9]SAP Input-BS'!$A$5:$F$502,5,0),0) -> 0.08 | G13: =IFERROR(VLOOKUP(E13,'[10]SAP Input-BS'!$A$5:$F$500,5,0),0) -> 0.04 | H13: =F13-G13 -> 0.04 | K13: =IFERROR(VLOOKUP(E13,'[11]SAP Input-BS'!$A$5:$E$500,5,0),0) -> -0.34 | L13: 0
A14: Current Assets | B14: Other current financial assets | C14: Marketable securities ≤ 1 y. | D14: Marketable securities ≤ 1 y - AC | E14: 17067 | F14: =IFERROR(VLOOKUP(E14,'[9]SAP Input-BS'!$A$5:$F$502,5,0),0) -> 0 | G14: =IFERROR(VLOOKUP(E14,'[10]SAP Input-BS'!$A$5:$F$500,5,0),0) -> 0 | H14: =F14-G14 -> 0 | K14: =IFERROR(VLOOKUP(E14,'[11]SAP Input-BS'!$A$5:$E$500,5,0),0) -> 0 | L14: 0
A15: Current Assets | B15: Other current financial assets | C15: Marketable securities ≤ 1 y. | D15: Other marketable securities ≤ 1 y - FVPL | E15: 17068 | F15: =IFERROR(VLOOKUP(E15,'[9]SAP Input-BS'!$A$5:$F$502,5,0),0) -> 0 | G15: =IFERROR(VLOOKUP(E15,'[10]SAP Input-BS'!$A$5:$F$500,5,0),0) -> 0 | H15: =F15-G15 -> 0 | K15: =IFERROR(VLOOKUP(E15,'[11]SAP Input-BS'!$A$5:$E$500,5,0),0) -> 0 | L15: 0
A16: Current Assets | B16: Other current financial assets | C16: Marketable securities ≤ 1 y. | D16: Total: Marketable securities ≤ 1 y. | E16: 17099 | F16: =IFERROR(VLOOKUP(E16,'[9]SAP Input-BS'!$A$5:$F$502,5,0),0) -> 1.1608765e+10 | G16: =IFERROR(VLOOKUP(E16,'[10]SAP Input-BS'!$A$5:$F$500,5,0),0) -> 1.4517035e+10 | H16: =F16-G16 -> -2.9082697e+09 | K16: =IFERROR(VLOOKUP(E16,'[11]SAP Input-BS'!$A$5:$E$500,5,0),0) -> 1.1601775e+10 | L16: 1.1390965e+10
A17: Current Assets | B17: Other current financial assets | C17: Loans | D17: Loans ≤ 1 y - 3rd, B-c, B-f | E17: 18210 | F17: =IFERROR(VLOOKUP(E17,'[9]SAP Input-BS'!$A$5:$F$502,5,0),0) -> 0 | G17: =IFERROR(VLOOKUP(E17,'[10]SAP Input-BS'!$A$5:$F$500,5,0),0) -> 0 | H17: =F17-G17 -> 0 | K17: =IFERROR(VLOOKUP(E17,'[11]SAP Input-BS'!$A$5:$E$500,5,0),0) -> 0 | L17: 0
A18: Current Assets | B18: Other current financial assets | C18: Loans | D18: Loans ≤ 1 y - employees | E18: 18215 | F18: =IFERROR(VLOOKUP(E18,'[9]SAP Input-BS'!$A$5:$F$502,5,0),0) -> 13515405 | G18: =IFERROR(VLOOKUP(E18,'[10]SAP Input-BS'!$A$5:$F$500,5,0),0) -> 12718628 | H18: =F18-G18 -> 796777.64 | K18: =IFERROR(VLOOKUP(E18,'[11]SAP Input-BS'!$A$5:$E$500,5,0),0) -> 11675401 | L18: 12537938
A19: Current Assets | B19: Other current financial assets | C19: Loans | D19: Loans ≤ 1 y - K | E19: 18220 | F19: =IFERROR(VLOOKUP(E19,'[9]SAP Input-BS'!$A$5:$F$502,5,0),0) -> 6147292000 | G19: =IFERROR(VLOOKUP(E19,'[10]SAP Input-BS'!$A$5:$F$500,5,0),0) -> 5218076388 | H19: =F19-G19 -> 929215612 | J19: ETAS,RBAI and MPIN | K19: =IFERROR(VLOOKUP(E19,'[11]SAP Input-BS'!$A$5:$E$500,5,0),0) -> 1813902000 | L19: 5263902000
A20: Current Assets | B20: Other current financial assets | C20: Loans | D20: Loans ≤ 1 y - N | E20: 18240 | F20: =IFERROR(VLOOKUP(E20,'[9]SAP Input-BS'!$A$5:$F$502,5,0),0) -> 0 | G20: =IFERROR(VLOOKUP(E20,'[10]SAP Input-BS'!$A$5:$F$500,5,0),0) -> 0 | H20: =F20-G20 -> 0 | K20: =IFERROR(VLOOKUP(E20,'[11]SAP Input-BS'!$A$5:$E$500,5,0),0) -> 0 | L20: 0
A21: Current Assets | B21: Other current financial assets | C21: Loans | D21: Loans ≤ 1 y - B-a | E21: 18260 | F21: =IFERROR(VLOOKUP(E21,'[9]SAP Input-BS'!$A$5:$F$502,5,0),0) -> 0 | G21: =IFERROR(VLOOKUP(E21,'[10]SAP Input-BS'!$A$5:$F$500,5,0),0) -> 0 | H21: =F21-G21 -> 0 | K21: =IFERROR(VLOOKUP(E21,'[11]SAP Input-BS'!$A$5:$E$500,5,0),0) -> 0 | L21: 0
A22: Current Assets | B22: Other current financial assets | C22: Loans | D22: Loans FVPL (not SPPI compliant) ≤ 1 y - 3rd, B-c, B-f | E22: 18280 | F22: =IFERROR(VLOOKUP(E22,'[9]SAP Input-BS'!$A$5:$F$502,5,0),0) -> 0 | G22: =IFERROR(VLOOKUP(E22,'[10]SAP Input-BS'!$A$5:$F$500,5,0),0) -> 0 | H22: =F22-G22 -> 0 | K22: =IFERROR(VLOOKUP(E22,'[11]SAP Input-BS'!$A$5:$E$500,5,0),0) -> 0 | L22: 0
A23: Current Assets | B23: Other current financial assets | C23: Loans | D23: Total: Loans ≤ 1 y | E23: 18299 | F23: =IFERROR(VLOOKUP(E23,'[9]SAP Input-BS'!$A$5:$F$502,5,0),0) -> 6.1608074e+09 | G23: =IFERROR(VLOOKUP(E23,'[10]SAP Input-BS'!$A$5:$F$500,5,0),0) -> 5.230795e+09 | H23: =F23-G23 -> 9.3001239e+08 | K23: =IFERROR(VLOOKUP(E23,'[11]SAP Input-BS'!$A$5:$E$500,5,0),0) -> 1.8255774e+09 | L23: 5.2764399e+09
A24: Current Assets | B24: Other current financial assets | C24: Financial clearing, cash pool | D24: Financial clearing, cash pool - K | E24: 18320 | F24: =IFERROR(VLOOKUP(E24,'[9]SAP Input-BS'!$A$5:$F$502,5,0),0) -> 0 | G24: =IFERROR(VLOOKUP(E24,'[10]SAP Input-BS'!$A$5:$F$500,5,0),0) -> 0 | H24: =F24-G24 -> 0 | K24: =IFERROR(VLOOKUP(E24,'[11]SAP Input-BS'!$A$5:$E$500,5,0),0) -> 0 | L24: 0
A25: Current Assets | B25: Other current financial assets | C25: Financial clearing, cash pool | D25: Financial clearing, cash pool - N | E25: 18340 | F25: =IFERROR(VLOOKUP(E25,'[9]SAP Input-BS'!$A$5:$F$502,5,0),0) -> 0 | G25: =IFERROR(VLOOKUP(E25,'[10]SAP Input-BS'!$A$5:$F$500,5,0),0) -> 0 | H25: =F25-G25 -> 0 | K25: =IFERROR(VLOOKUP(E25,'[11]SAP Input-BS'!$A$5:$E$500,5,0),0) -> 0 | L25: 0
A26: Current Assets | B26: Other current financial assets | C26: Financial clearing, cash pool | D26: Finanzclearing, cash pool - B-a | E26: 18360 | F26: =IFERROR(VLOOKUP(E26,'[9]SAP Input-BS'!$A$5:$F$502,5,0),0) -> 0 | G26: =IFERROR(VLOOKUP(E26,'[10]SAP Input-BS'!$A$5:$F$500,5,0),0) -> 0 | H26: =F26-G26 -> 0 | K26: =IFERROR(VLOOKUP(E26,'[11]SAP Input-BS'!$A$5:$E$500,5,0),0) -> 0 | L26: 0
A27: Current Assets | B27: Other current financial assets | C27: Financial clearing, cash pool | D27: Finanzclearing, cash pool - B-c, B-f | E27: 18370 | F27: =IFERROR(VLOOKUP(E27,'[9]SAP Input-BS'!$A$5:$F$502,5,0),0) -> 0 | G27: =IFERROR(VLOOKUP(E27,'[10]SAP Input-BS'!$A$5:$F$500,5,0),0) -> 0 | H27: =F27-G27 -> 0 | K27: =IFERROR(VLOOKUP(E27,'[11]SAP Input-BS'!$A$5:$E$500,5,0),0) -> 0 | L27: 0
A28: Current Assets | B28: Other current financial assets | C28: Financial clearing, cash pool | D28: Total: Financial clearing, cash pool | E28: 18399 | F28: =IFERROR(VLOOKUP(E28,'[9]SAP Input-BS'!$A$5:$F$502,5,0),0) -> 0 | G28: =IFERROR(VLOOKUP(E28,'[10]SAP Input-BS'!$A$5:$F$500,5,0),0) -> 0 | H28: =F28-G28 -> 0 | K28: =IFERROR(VLOOKUP(E28,'[11]SAP Input-BS'!$A$5:$E$500,5,0),0) -> 0 | L28: 0
A29: Current Assets | B29: Other current financial assets | C29: Lease Receivables | D29: Receivables f. fin. lease (lessor) ≤ 1 y | E29: 18600 | F29: =IFERROR(VLOOKUP(E29,'[9]SAP Input-BS'!$A$5:$F$502,5,0),0) -> 3.9596487e+08 | G29: =IFERROR(VLOOKUP(E29,'[10]SAP Input-BS'!$A$5:$F$500,5,0),0) -> 3.9596487e+08 | H29: =F29-G29 -> 0 | K29: =IFERROR(VLOOKUP(E29,'[11]SAP Input-BS'!$A$5:$E$500,5,0),0) -> 6.62 | L29: 3.8461862e+08
A30: Current Assets | B30: Other current financial assets | C30: Derivative Assets | D30: Derivatives w/o hedge ≤ 1 y - 3rd | E30: 18603 | F30: =IFERROR(VLOOKUP(E30,'[9]SAP Input-BS'!$A$5:$F$502,5,0),0) -> 0 | G30: =IFERROR(VLOOKUP(E30,'[10]SAP Input-BS'!$A$5:$F$500,5,0),0) -> 0 | H30: =F30-G30 -> 0 | K30: =IFERROR(VLOOKUP(E30,'[11]SAP Input-BS'!$A$5:$E$500,5,0),0) -> 252393768 | L30: 0
A31: Current Assets | B31: Other current financial assets | C31: Travel Advances | D31: Fin. receivables board members, employees ≤ 1 y | E31: 18516 | F31: =IFERROR(VLOOKUP(E31,'[9]SAP Input-BS'!$A$5:$F$502,5,0),0) -> 5.7511126e+08 | G31: =IFERROR(VLOOKUP(E31,'[10]SAP Input-BS'!$A$5:$F$500,5,0),0) -> 1.8241202e+08 | H31: =F31-G31 -> 3.9269923e+08 | K31: =IFERROR(VLOOKUP(E31,'[11]SAP Input-BS'!$A$5:$E$500,5,0),0) -> 2.3600357e+08 | L31: 2.307519e+08
... A34: Current Assets | B34: Other current financial assets | C34: Accrued Interest (3rd party) | D34: Receivables accrued interest - 3rd, B-c, B-f | E34: 18615 | F34: =IFERROR(VLOOKUP(E34,'[9]SAP Input-BS'!$A$5:$F$502,5,0),0) -> 0 | G34: =IFERROR(VLOOKUP(E34,'[10]SAP Input-BS'!$A$5:$F$500,5,0),0) -> 0 | H34: =F34-G34 -> 0 | K34: =IFERROR(VLOOKUP(E34,'[11]SAP Input-BS'!$A$5:$E$500,5,0),0) -> 0 | L34: 0
A35: Current Assets | B35: Other current financial assets | C35: Deposits Receivable | D35: Other financial receivables ≤ 1 year third parties, B-c, B-f | E35: 18616 | F35: =IFERROR(VLOOKUP(E35,'[9]SAP Input-BS'!$A$5:$F$502,5,0),0) -> 5.3267149e+08 | G35: =IFERROR(VLOOKUP(E35,'[10]SAP Input-BS'!$A$5:$F$500,5,0),0) -> 2.762204e+08 | H35: =F35-G35 -> 256451092 | J35: Deposits, Escrow receipt | K35: =IFERROR(VLOOKUP(E35,'[11]SAP Input-BS'!$A$5:$E$500,5,0),0) -> 2.1089857e+08 | L35: 9.0024995e+09
A36: Current Assets | B36: Other current financial assets | C36: Dividend Receivables (ICR) | D36: Receivables PTA/dividends - K | E36: 18621 | F36: =IFERROR(VLOOKUP(E36,'[9]SAP Input-BS'!$A$5:$F$502,5,0),0) -> 0 | G36: =IFERROR(VLOOKUP(E36,'[10]SAP Input-BS'!$A$5:$F$500,5,0),0) -> 0 | H36: =F36-G36 -> 0 | K36: =IFERROR(VLOOKUP(E36,'[11]SAP Input-BS'!$A$5:$E$500,5,0),0) -> 0 | L36: 0
A37: Current Assets | B37: Other current financial assets | C37: Debit Balances - Creditors (ICR) | D37: Creditors with debit balances - K | E37: 18624 | F37: =IFERROR(VLOOKUP(E37,'[9]SAP Input-BS'!$A$5:$F$502,5,0),0) -> 58775 | G37: =IFERROR(VLOOKUP(E37,'[10]SAP Input-BS'!$A$5:$F$500,5,0),0) -> 46786 | H37: =F37-G37 -> 11989 | K37: =IFERROR(VLOOKUP(E37,'[11]SAP Input-BS'!$A$5:$E$500,5,0),0) -> 11142113 | L37: 21800085
A38: Current Assets | B38: Other current financial assets | C38: Accrued Interest (ICR) | D38: Receivables accrued interest - K | E38: 18625 | F38: =IFERROR(VLOOKUP(E38,'[9]SAP Input-BS'!$A$5:$F$502,5,0),0) -> 1721239.4 | G38: =IFERROR(VLOOKUP(E38,'[10]SAP Input-BS'!$A$5:$F$500,5,0),0) -> 1284707.1 | H38: =F38-G38 -> 436532.31 | K38: =IFERROR(VLOOKUP(E38,'[11]SAP Input-BS'!$A$5:$E$500,5,0),0) -> 119086.89 | L38: 462724.78
A39: Current Assets | B39: Other current financial assets | D39: Other financial receivables ≤ 1 y - K | E39: 18626 | F39: =IFERROR(VLOOKUP(E39,'[9]SAP Input-BS'!$A$5:$F$502,5,0),0) -> 0 | G39: =IFERROR(VLOOKUP(E39,'[10]SAP Input-BS'!$A$5:$F$500,5,0),0) -> 0 | H39: =F39-G39 -> 0 | K39: =IFERROR(VLOOKUP(E39,'[11]SAP Input-BS'!$A$5:$E$500,5,0),0) -> 0 | L39: 0
A40: Current Assets | B40: Other current financial assets | D40: Receivables PTA/dividends - N | E40: 18641 | F40: =IFERROR(VLOOKUP(E40,'[9]SAP Input-BS'!$A$5:$F$502,5,0),0) -> 0 | G40: =IFERROR(VLOOKUP(E40,'[10]SAP Input-BS'!$A$5:$F$500,5,0),0) -> 0 | H40: =F40-G40 -> 0 | K40: =IFERROR(VLOOKUP(E40,'[11]SAP Input-BS'!$A$5:$E$500,5,0),0) -> 0 | L40: 0
A41: Current Assets | B41: Other current financial assets | C41: Debit Balances - Creditors (3rd Party) | D41: Creditors with debit balances - N | E41: 18644 | F41: =IFERROR(VLOOKUP(E41,'[9]SAP Input-BS'!$A$5:$F$502,5,0),0) -> 0 | G41: =IFERROR(VLOOKUP(E41,'[10]SAP Input-BS'!$A$5:$F$500,5,0),0) -> 2100157 | H41: =F41-G41 -> -2100157 | K41: =IFERROR(VLOOKUP(E41,'[11]SAP Input-BS'!$A$5:$E$500,5,0),0) -> 1731827.8 | L41: 1731827.8
A42: Current Assets | B42: Other current financial assets | D42: Receivables accrued interest - N | E42: 18645 | F42: =IFERROR(VLOOKUP(E42,'[9]SAP Input-BS'!$A$5:$F$502,5,0),0) -> 0 | G42: =IFERROR(VLOOKUP(E42,'[10]SAP Input-BS'!$A$5:$F$500,5,0),0) -> 0 | H42: =F42-G42 -> 0 | K42: =IFERROR(VLOOKUP(E42,'[11]SAP Input-BS'!$A$5:$E$500,5,0),0) -> 0 | L42: 0
A43: Current Assets | B43: Other current financial assets | D43: Other financial receivables ≤ 1 y - N | E43: 18646 | F43: =IFERROR(VLOOKUP(E43,'[9]SAP Input-BS'!$A$5:$F$502,5,0),0) -> 0 | G43: =IFERROR(VLOOKUP(E43,'[10]SAP Input-BS'!$A$5:$F$500,5,0),0) -> 0 | H43: =F43-G43 -> 0 | K43: =IFERROR(VLOOKUP(E43,'[11]SAP Input-BS'!$A$5:$E$500,5,0),0) -> 0 | L43: 0
A44: Current Assets | B44: Other current financial assets | D44: Receivables dividends - B-a | E44: 18661 | F44: =IFERROR(VLOOKUP(E44,'[9]SAP Input-BS'!$A$5:$F$502,5,0),0) -> 0 | G44: =IFERROR(VLOOKUP(E44,'[10]SAP Input-BS'!$A$5:$F$500,5,0),0) -> 0 | H44: =F44-G44 -> 0 | K44: =IFERROR(VLOOKUP(E44,'[11]SAP Input-BS'!$A$5:$E$500,5,0),0) -> 0 | L44: 0
A45: Current Assets | B45: Other current financial assets | D45: Creditors with debit balances - B-a | E45: 18664 | F45: =IFERROR(VLOOKUP(E45,'[9]SAP Input-BS'!$A$5:$F$502,5,0),0) -> 0 | G45: =IFERROR(VLOOKUP(E45,'[10]SAP Input-BS'!$A$5:$F$500,5,0),0) -> 0 | H45: =F45-G45 -> 0 | K45: =IFERROR(VLOOKUP(E45,'[11]SAP Input-BS'!$A$5:$E$500,5,0),0) -> 0 | L45: 0
A46: Current Assets | B46: Other current financial assets | D46: Receivables accrued interest - B-a | E46: 18665 | F46: =IFERROR(VLOOKUP(E46,'[9]SAP Input-BS'!$A$5:$F$502,5,0),0) -> 0 | G46: =IFERROR(VLOOKUP(E46,'[10]SAP Input-BS'!$A$5:$F$500,5,0),0) -> 0 | H46: =F46-G46 -> 0 | K46: =IFERROR(VLOOKUP(E46,'[11]SAP Input-BS'!$A$5:$E$500,5,0),0) -> 0 | L46: 0
A47: Current Assets | B47: Other current financial assets | D47: Other financial receivables ≤ 1 y - B-a | E47: 18666 | F47: =IFERROR(VLOOKUP(E47,'[9]SAP Input-BS'!$A$5:$F$502,5,0),0) -> 0 | G47: =IFERROR(VLOOKUP(E47,'[10]SAP Input-BS'!$A$5:$F$500,5,0),0) -> 0 | H47: =F47-G47 -> 0 | K47: =IFERROR(VLOOKUP(E47,'[11]SAP Input-BS'!$A$5:$E$500,5,0),0) -> 0 | L47: 0
A48: Current Assets | B48: Other current financial assets | C48: Other current financial assets | D48: Total: Other current financial assets | E48: AC_FA | F48: =IFERROR(VLOOKUP(E48,'[9]SAP Input-BS'!$A$5:$F$502,5,0),0) -> 1.92751e+10 | G48: =IFERROR(VLOOKUP(E48,'[10]SAP Input-BS'!$A$5:$F$500,5,0),0) -> 2.0605859e+10 | H48: =F48-G48 -> -1.3307586e+09 | K48: =IFERROR(VLOOKUP(E48,'[11]SAP Input-BS'!$A$5:$E$500,5,0),0) -> 2.6478047e+10 | L48: 2.630927e+10
A49: Current Assets | B49: Contract assets (CA) ≤ 1 y | D49: CA: Sales over time ≤ 1 y - 3rd, N, B-a, B-c, B-f | E49: 18700 | F49: =IFERROR(VLOOKUP(E49,'[9]SAP Input-BS'!$A$5:$F$502,5,0),0) -> 0 | G49: =IFERROR(VLOOKUP(E49,'[10]SAP Input-BS'!$A$5:$F$500,5,0),0) -> 0 | H49: =F49-G49 -> 0 | K49: =IFERROR(VLOOKUP(E49,'[11]SAP Input-BS'!$A$5:$E$500,5,0),0) -> 0 | L49: 0
A50: Current Assets | B50: Contract assets (CA) ≤ 1 y | D50: CA: Other ≤ 1 y - 3rd, N, B-a, B-c, B-f | E50: 18701 | F50: =IFERROR(VLOOKUP(E50,'[9]SAP Input-BS'!$A$5:$F$502,5,0),0) -> 0 | G50: =IFERROR(VLOOKUP(E50,'[10]SAP Input-BS'!$A$5:$F$500,5,0),0) -> 0 | H50: =F50-G50 -> 0 | K50: =IFERROR(VLOOKUP(E50,'[11]SAP Input-BS'!$A$5:$E$500,5,0),0) -> 0 | L50: 0
A51: Current Assets | B51: Contract assets (CA) ≤ 1 y | D51: CA: R&D contracts ≤ 1 y - 3rd, B-a, B-c, B-f | E51: 18704 | F51: =IFERROR(VLOOKUP(E51,'[9]SAP Input-BS'!$A$5:$F$502,5,0),0) -> 0 | G51: =IFERROR(VLOOKUP(E51,'[10]SAP Input-BS'!$A$5:$F$500,5,0),0) -> 0 | H51: =F51-G51 -> 0 | K51: =IFERROR(VLOOKUP(E51,'[11]SAP Input-BS'!$A$5:$E$500,5,0),0) -> 0 | L51: 0
A52: Current Assets | B52: Contract assets (CA) ≤ 1 y | D52: CA: R&D contracts ≤ 1 y - N | E52: 18740 | F52: =IFERROR(VLOOKUP(E52,'[9]SAP Input-BS'!$A$5:$F$502,5,0),0) -> 0 | G52: =IFERROR(VLOOKUP(E52,'[10]SAP Input-BS'!$A$5:$F$500,5,0),0) -> 0 | H52: =F52-G52 -> 0 | K52: =IFERROR(VLOOKUP(E52,'[11]SAP Input-BS'!$A$5:$E$500,5,0),0) -> 0 | L52: 0
A53: Current Assets | B53: Contract assets (CA) ≤ 1 y | C53: Contract assets (CA) ≤ 1 y | D53: Total: Contract assets (CA) ≤ 1 y | E53: AC_CA | F53: =IFERROR(VLOOKUP(E53,'[9]SAP Input-BS'!$A$5:$F$502,5,0),0) -> 0 | G53: =IFERROR(VLOOKUP(E53,'[10]SAP Input-BS'!$A$5:$F$500,5,0),0) -> 0 | H53: =F53-G53 -> 0 | K53: =IFERROR(VLOOKUP(E53,'[11]SAP Input-BS'!$A$5:$E$500,5,0),0) -> 0 | L53: 0
A54: Current Assets | B54: Income tax receivables ≤ 1 y | C54: Income tax receivables ≤ 1 y | D54: Income tax receivables ≤ 1 y | E54: 18510 | F54: =IFERROR(VLOOKUP(E54,'[9]SAP Input-BS'!$A$5:$F$502,5,0),0) -> 0 | G54: =IFERROR(VLOOKUP(E54,'[10]SAP Input-BS'!$A$5:$F$500,5,0),0) -> -229921.71 | H54: =F54-G54 -> 229921.71 | K54: =IFERROR(VLOOKUP(E54,'[11]SAP Input-BS'!$A$5:$E$500,5,0),0) -> 1.7517443e+09 | L54: 42030080
A55: Current Assets | B55: Income tax receivables ≤ 1 y | C55: Income tax receivables ≤ 1 y | D55: Total: Income tax receivables ≤ 1 y | E55: AC_IT | F55: =IFERROR(VLOOKUP(E55,'[9]SAP Input-BS'!$A$5:$F$502,5,0),0) -> 0 | G55: =IFERROR(VLOOKUP(E55,'[10]SAP Input-BS'!$A$5:$F$500,5,0),0) -> -229921.71 | H55: =F55-G55 -> 229921.71 | K55: =IFERROR(VLOOKUP(E55,'[11]SAP Input-BS'!$A$5:$E$500,5,0),0) -> 1.7517443e+09 | L55: 42030080
A56: Current Assets | B56: Other current receivables | C56: Prepaid Expenses | D56: Prepaid expenses ≤ 1 y - 3rd, N, B-a, B-c, B-f | E56: 18400 | F56: =IFERROR(VLOOKUP(E56,'[9]SAP Input-BS'!$A$5:$F$502,5,0),0) -> 219275331 | G56: =IFERROR(VLOOKUP(E56,'[10]SAP Input-BS'!$A$5:$F$500,5,0),0) -> 323015395 | H56: =F56-G56 -> -103740064 | K56: =IFERROR(VLOOKUP(E56,'[11]SAP Input-BS'!$A$5:$E$500,5,0),0) -> 1.3805269e+08 | L56: 5.3345212e+08
A57: Current Assets | B57: Other current receivables | D57: Prepaid expenses ≤ 1 y - K | E57: 18410 | F57: =IFERROR(VLOOKUP(E57,'[9]SAP Input-BS'!$A$5:$F$502,5,0),0) -> 0 | G57: =IFERROR(VLOOKUP(E57,'[10]SAP Input-BS'!$A$5:$F$500,5,0),0) -> 0 | H57: =F57-G57 -> 0 | K57: =IFERROR(VLOOKUP(E57,'[11]SAP Input-BS'!$A$5:$E$500,5,0),0) -> 0 | L57: 0
A58: Current Assets | B58: Other current receivables | D58: Special payments to suppliers ≤ 1 y | E58: 18470 | F58: =IFERROR(VLOOKUP(E58,'[9]SAP Input-BS'!$A$5:$F$502,5,0),0) -> 0 | G58: =IFERROR(VLOOKUP(E58,'[10]SAP Input-BS'!$A$5:$F$500,5,0),0) -> 0 | H58: =F58-G58 -> 0 | K58: =IFERROR(VLOOKUP(E58,'[11]SAP Input-BS'!$A$5:$E$500,5,0),0) -> 0 | L58: 0
A59: Current Assets | B59: Other current receivables | C59: GST receivables | D59: Other tax receivables ≤ 1 y | E59: 18511 | F59: =IFERROR(VLOOKUP(E59,'[9]SAP Input-BS'!$A$5:$F$502,5,0),0) -> 3610388.8 | G59: =IFERROR(VLOOKUP(E59,'[10]SAP Input-BS'!$A$5:$F$500,5,0),0) -> -16945483 | H59: =F59-G59 -> 20555872 | K59: =IFERROR(VLOOKUP(E59,'[11]SAP Input-BS'!$A$5:$E$500,5,0),0) -> 4713224.1 | L59: 3724193.4
A60: Current Assets | B60: Other current receivables | D60: Other receivables board members, employees ≤ 1 y | E60: 18515 | F60: =IFERROR(VLOOKUP(E60,'[9]SAP Input-BS'!$A$5:$F$502,5,0),0) -> 3305554.4 | G60: =IFERROR(VLOOKUP(E60,'[10]SAP Input-BS'!$A$5:$F$500,5,0),0) -> 8138.41 | H60: =F60-G60 -> 3297416 | K60: =IFERROR(VLOOKUP(E60,'[11]SAP Input-BS'!$A$5:$E$500,5,0),0) -> 8138.41 | L60: 8138
A61: Current Assets | B61: Other current receivables | D61: Receivables from interest on tax rec. ≤ 1 y | E61: 18604 | F61: =IFERROR(VLOOKUP(E61,'[9]SAP Input-BS'!$A$5:$F$502,5,0),0) -> 0 | G61: =IFERROR(VLOOKUP(E61,'[10]SAP Input-BS'!$A$5:$F$500,5,0),0) -> 0 | H61: =F61-G61 -> 0 | K61: =IFERROR(VLOOKUP(E61,'[11]SAP Input-BS'!$A$5:$E$500,5,0),0) -> 0 | L61: 0
A62: Current Assets | B62: Other current receivables | D62: Sundry other receivables ≤ 1 y - 3rd, B-c, B-f | E62: 18610 | F62: =IFERROR(VLOOKUP(E62,'[9]SAP Input-BS'!$A$5:$F$502,5,0),0) -> 1.3217464e+08 | G62: =IFERROR(VLOOKUP(E62,'[10]SAP Input-BS'!$A$5:$F$500,5,0),0) -> 62300475 | H62: =F62-G62 -> 69874162 | K62: =IFERROR(VLOOKUP(E62,'[11]SAP Input-BS'!$A$5:$E$500,5,0),0) -> 1.644555e+08 | L62: 1.4622442e+08
A63: Current Assets | B63: Other current receivables | D63: Down payment made for other services - 3rd, B-c, B-f | E63: 18618 | F63: =IFERROR(VLOOKUP(E63,'[9]SAP Input-BS'!$A$5:$F$502,5,0),0) -> 71307984 | G63: =IFERROR(VLOOKUP(E63,'[10]SAP Input-BS'!$A$5:$F$500,5,0),0) -> 1.1228803e+08 | H63: =F63-G63 -> -40980043 | K63: =IFERROR(VLOOKUP(E63,'[11]SAP Input-BS'!$A$5:$E$500,5,0),0) -> 2.8661085e+08 | L63: 1.3627723e+08
A64: Current Assets | B64: Other current receivables | D64: Sundry other receivables ≤ 1 y - K | E64: 18620 | F64: =IFERROR(VLOOKUP(E64,'[9]SAP Input-BS'!$A$5:$F$502,5,0),0) -> 0 | G64: =IFERROR(VLOOKUP(E64,'[10]SAP Input-BS'!$A$5:$F$500,5,0),0) -> 0 | H64: =F64-G64 -> 0 | K64: =IFERROR(VLOOKUP(E64,'[11]SAP Input-BS'!$A$5:$E$500,5,0),0) -> 0 | L64: 0
A65: Current Assets | B65: Other current receivables | D65: Receivables tax consolidation - K | E65: 18622 | F65: =IFERROR(VLOOKUP(E65,'[9]SAP Input-BS'!$A$5:$F$502,5,0),0) -> 0 | G65: =IFERROR(VLOOKUP(E65,'[10]SAP Input-BS'!$A$5:$F$500,5,0),0) -> 0 | H65: =F65-G65 -> 0 | K65: =IFERROR(VLOOKUP(E65,'[11]SAP Input-BS'!$A$5:$E$500,5,0),0) -> 0 | L65: 0
A66: Current Assets | B66: Other current receivables | D66: Capitalized Costs to fulfil a contract < 1 y - 3rd, N, B-a, B-c, B-f | E66: 18623 | F66: =IFERROR(VLOOKUP(E66,'[9]SAP Input-BS'!$A$5:$F$502,5,0),0) -> 0 | G66: =IFERROR(VLOOKUP(E66,'[10]SAP Input-BS'!$A$5:$F$500,5,0),0) -> 0 | H66: =F66-G66 -> 0 | K66: =IFERROR(VLOOKUP(E66,'[11]SAP Input-BS'!$A$5:$E$500,5,0),0) -> 62449155 | L66: 0
A67: Current Assets | B67: Other current receivables | D67: Quick savings ≤ 1 y - 3rd, N, B-a, B-c, B-f | E67: 18627 | F67: =IFERROR(VLOOKUP(E67,'[9]SAP Input-BS'!$A$5:$F$502,5,0),0) -> 0 | G67: =IFERROR(VLOOKUP(E67,'[10]SAP Input-BS'!$A$5:$F$500,5,0),0) -> 0 | H67: =F67-G67 -> 0 | K67: =IFERROR(VLOOKUP(E67,'[11]SAP Input-BS'!$A$5:$E$500,5,0),0) -> 0 | L67: 0
A68: Current Assets | B68: Other current receivables | D68: Down payment made for other services - K | E68: 18628 | F68: =IFERROR(VLOOKUP(E68,'[9]SAP Input-BS'!$A$5:$F$502,5,0),0) -> 0 | G68: =IFERROR(VLOOKUP(E68,'[10]SAP Input-BS'!$A$5:$F$500,5,0),0) -> 0 | H68: =F68-G68 -> 0 | K68: =IFERROR(VLOOKUP(E68,'[11]SAP Input-BS'!$A$5:$E$500,5,0),0) -> 0 | L68: 0
A69: Current Assets | B69: Other current receivables | D69: Sundry other receivables ≤ 1 y - N | E69: 18640 | F69: =IFERROR(VLOOKUP(E69,'[9]SAP Input-BS'!$A$5:$F$502,5,0),0) -> 0 | G69: =IFERROR(VLOOKUP(E69,'[10]SAP Input-BS'!$A$5:$F$500,5,0),0) -> 0 | H69: =F69-G69 -> 0 | K69: =IFERROR(VLOOKUP(E69,'[11]SAP Input-BS'!$A$5:$E$500,5,0),0) -> 0 | L69: 0
A70: Current Assets | B70: Other current receivables | D70: Receivables tax consolidation - N | E70: 18642 | F70: =IFERROR(VLOOKUP(E70,'[9]SAP Input-BS'!$A$5:$F$502,5,0),0) -> 0 | G70: =IFERROR(VLOOKUP(E70,'[10]SAP Input-BS'!$A$5:$F$500,5,0),0) -> 0 | H70: =F70-G70 -> 0 | K70: =IFERROR(VLOOKUP(E70,'[11]SAP Input-BS'!$A$5:$E$500,5,0),0) -> 0 | L70: 0
A71: Current Assets | B71: Other current receivables | D71: Down payment made for other services - N | E71: 18648 | F71: =IFERROR(VLOOKUP(E71,'[9]SAP Input-BS'!$A$5:$F$502,5,0),0) -> 0 | G71: =IFERROR(VLOOKUP(E71,'[10]SAP Input-BS'!$A$5:$F$500,5,0),0) -> 0 | H71: =F71-G71 -> 0 | K71: =IFERROR(VLOOKUP(E71,'[11]SAP Input-BS'!$A$5:$E$500,5,0),0) -> 0 | L71: 0
... A73: Current Assets | B73: Other current receivables | D73: Down payment made for other services - B-a | E73: 18668 | F73: =IFERROR(VLOOKUP(E73,'[9]SAP Input-BS'!$A$5:$F$502,5,0),0) -> 0 | G73: =IFERROR(VLOOKUP(E73,'[10]SAP Input-BS'!$A$5:$F$500,5,0),0) -> 0 | H73: =F73-G73 -> 0 | K73: =IFERROR(VLOOKUP(E73,'[11]SAP Input-BS'!$A$5:$E$500,5,0),0) -> 0 | L73: 0
A74: Current Assets | B74: Other current receivables | C74: Other current assets | D74: Total: Other current assets | E74: AC_OA | F74: =IFERROR(VLOOKUP(E74,'[9]SAP Input-BS'!$A$5:$F$502,5,0),0) -> 4.296739e+08 | G74: =IFERROR(VLOOKUP(E74,'[10]SAP Input-BS'!$A$5:$F$500,5,0),0) -> 4.8066655e+08 | H74: =F74-G74 -> -50992656 | K74: =IFERROR(VLOOKUP(E74,'[11]SAP Input-BS'!$A$5:$E$500,5,0),0) -> 6.5628956e+08 | L74: 8.1968611e+08
A75: Current Assets | B75: Inventories | C75: Inventories | D75: Total: Inventories | E75: AC_IV | F75: =IFERROR(VLOOKUP(E75,'[9]SAP Input-BS'!$A$5:$F$502,5,0),0) -> 1.3243591e+08 | G75: =IFERROR(VLOOKUP(E75,'[10]SAP Input-BS'!$A$5:$F$500,5,0),0) -> 1.0927177e+08 | H75: =F75-G75 -> 23164139 | K75: =IFERROR(VLOOKUP(E75,'[11]SAP Input-BS'!$A$5:$E$500,5,0),0) -> 1.7281624e+08 | L75: 1.7435118e+08
A76: Current Assets | B76: Total: Current assets | C76: Total: Current assets | D76: Total: Current assets | E76: AC_TO | F76: =IFERROR(VLOOKUP(E76,'[9]SAP Input-BS'!$A$5:$F$502,5,0),0) -> 4.6424056e+10 | G76: =IFERROR(VLOOKUP(E76,'[10]SAP Input-BS'!$A$5:$F$500,5,0),0) -> 4.6555971e+10 | H76: =F76-G76 -> -1.319154e+08 | K76: =IFERROR(VLOOKUP(E76,'[11]SAP Input-BS'!$A$5:$E$500,5,0),0) -> 5.1845012e+10 | L76: 5.3865272e+10
F77: =IFERROR(VLOOKUP(E77,'[9]SAP Input-BS'!$A$5:$F$502,5,0),0) -> 0 | G77: =IFERROR(VLOOKUP(E77,'[10]SAP Input-BS'!$A$5:$F$500,5,0),0) -> 0 | H77: =F77-G77 -> 0
A78: Non-current assets | B78: Other non-current financial assets > 1 y | C78: Marketable securities > 1 y. | D78: Stocks - FVOCI nR | E78: 15100 | F78: =IFERROR(VLOOKUP(E78,'[9]SAP Input-BS'!$A$5:$F$502,5,0),0) -> 0 | G78: =IFERROR(VLOOKUP(E78,'[10]SAP Input-BS'!$A$5:$F$500,5,0),0) -> 0 | H78: =F78-G78 -> 0 | K78: =IFERROR(VLOOKUP(E78,'[11]SAP Input-BS'!$A$5:$E$500,5,0),0) -> 0 | L78: 0
A79: Non-current assets | B79: Other non-current financial assets > 1 y | C79: Marketable securities > 1 y. | D79: Marketable securities > 1 y - FVOCI wR | E79: 15102 | F79: =IFERROR(VLOOKUP(E79,'[9]SAP Input-BS'!$A$5:$F$502,5,0),0) -> 0 | G79: =IFERROR(VLOOKUP(E79,'[10]SAP Input-BS'!$A$5:$F$500,5,0),0) -> 0 | H79: =F79-G79 -> 0 | K79: =IFERROR(VLOOKUP(E79,'[11]SAP Input-BS'!$A$5:$E$500,5,0),0) -> 0 | L79: 0
A80: Non-current assets | B80: Other non-current financial assets > 1 y | C80: Marketable securities > 1 y. | D80: Marketable securities > 1 y - AC | E80: 15105 | F80: =IFERROR(VLOOKUP(E80,'[9]SAP Input-BS'!$A$5:$F$502,5,0),0) -> 0 | G80: =IFERROR(VLOOKUP(E80,'[10]SAP Input-BS'!$A$5:$F$500,5,0),0) -> 0 | H80: =F80-G80 -> 0 | K80: =IFERROR(VLOOKUP(E80,'[11]SAP Input-BS'!$A$5:$E$500,5,0),0) -> 0 | L80: 0
A81: Non-current assets | B81: Other non-current financial assets > 1 y | C81: Marketable securities > 1 y. | D81: Marketable securities others > 1 y - FVPL | E81: 15106 | F81: =IFERROR(VLOOKUP(E81,'[9]SAP Input-BS'!$A$5:$F$502,5,0),0) -> 0 | G81: =IFERROR(VLOOKUP(E81,'[10]SAP Input-BS'!$A$5:$F$500,5,0),0) -> 0 | H81: =F81-G81 -> 0 | K81: =IFERROR(VLOOKUP(E81,'[11]SAP Input-BS'!$A$5:$E$500,5,0),0) -> 0 | L81: 0
A82: Non-current assets | B82: Other non-current financial assets > 1 y | C82: Marketable securities > 1 y. | D82: Investment funds - FVPL | E82: 15107 | F82: =IFERROR(VLOOKUP(E82,'[9]SAP Input-BS'!$A$5:$F$502,5,0),0) -> 0 | G82: =IFERROR(VLOOKUP(E82,'[10]SAP Input-BS'!$A$5:$F$500,5,0),0) -> 0 | H82: =F82-G82 -> 0 | K82: =IFERROR(VLOOKUP(E82,'[11]SAP Input-BS'!$A$5:$E$500,5,0),0) -> 0 | L82: 0
A83: Non-current assets | B83: Other non-current financial assets > 1 y | C83: Marketable securities > 1 y. | D83: Total: Marketable securities > 1 y. | E83: 15109 | F83: =IFERROR(VLOOKUP(E83,'[9]SAP Input-BS'!$A$5:$F$502,5,0),0) -> 0 | G83: =IFERROR(VLOOKUP(E83,'[10]SAP Input-BS'!$A$5:$F$500,5,0),0) -> 0 | H83: =F83-G83 -> 0 | K83: =IFERROR(VLOOKUP(E83,'[11]SAP Input-BS'!$A$5:$E$500,5,0),0) -> 0 | L83: 0
A84: Non-current assets | B84: Other non-current financial assets > 1 y | C84: Investments (wo B-a) | D84: Total: Investments (wo B-a) | E84: AN_IN | F84: =IFERROR(VLOOKUP(E84,'[9]SAP Input-BS'!$A$5:$F$502,5,0),0) -> 1.5142792e+10 | G84: =IFERROR(VLOOKUP(E84,'[10]SAP Input-BS'!$A$5:$F$500,5,0),0) -> 1.8830801e+10 | H84: =F84-G84 -> -3.6880092e+09 | J84: page A.FA | K84: =IFERROR(VLOOKUP(E84,'[11]SAP Input-BS'!$A$5:$E$500,5,0),0) -> 14577647253 | L84: 1.8396416e+10
A85: Non-current assets | B85: Other non-current financial assets > 1 y | C85: Bank balances > 1 y | D85: Total: Bank balances > 1 y | E85: 15051 | F85: =IFERROR(VLOOKUP(E85,'[9]SAP Input-BS'!$A$5:$F$502,5,0),0) -> 0 | G85: =IFERROR(VLOOKUP(E85,'[10]SAP Input-BS'!$A$5:$F$500,5,0),0) -> 0 | H85: =F85-G85 -> 0 | K85: =IFERROR(VLOOKUP(E85,'[11]SAP Input-BS'!$A$5:$E$500,5,0),0) -> 0 | L85: 0
A86: Non-current assets | B86: Other non-current financial assets > 1 y | C86: Loans | D86: Loans > 1 y - 3rd, B-c, B-f | E86: 15210 | F86: =IFERROR(VLOOKUP(E86,'[9]SAP Input-BS'!$A$5:$F$502,5,0),0) -> 8.5346737e+08 | G86: =IFERROR(VLOOKUP(E86,'[10]SAP Input-BS'!$A$5:$F$500,5,0),0) -> 4.7097848e+08 | H86: =F86-G86 -> 382488889 | J86: GMR | K86: =IFERROR(VLOOKUP(E86,'[11]SAP Input-BS'!$A$5:$E$500,5,0),0) -> 3.2298333e+08 | L86: 4.6382682e+08
A87: Non-current assets | B87: Other non-current financial assets > 1 y | C87: Loans | D87: Loans > 1 y - employees | E87: 15215 | F87: =IFERROR(VLOOKUP(E87,'[9]SAP Input-BS'!$A$5:$F$502,5,0),0) -> 71116272 | G87: =IFERROR(VLOOKUP(E87,'[10]SAP Input-BS'!$A$5:$F$500,5,0),0) -> 71780813 | H87: =F87-G87 -> -664541 | K87: =IFERROR(VLOOKUP(E87,'[11]SAP Input-BS'!$A$5:$E$500,5,0),0) -> 70852420 | L87: 69384446
A88: Non-current assets | B88: Other non-current financial assets > 1 y | C88: Loans | D88: Loans > 1 y - K | E88: 15220 | F88: =IFERROR(VLOOKUP(E88,'[9]SAP Input-BS'!$A$5:$F$502,5,0),0) -> 46610000 | G88: =IFERROR(VLOOKUP(E88,'[10]SAP Input-BS'!$A$5:$F$500,5,0),0) -> 46610000 | H88: =F88-G88 -> 0 | J88: BGSG | K88: =IFERROR(VLOOKUP(E88,'[11]SAP Input-BS'!$A$5:$E$500,5,0),0) -> 0 | L88: 0
A89: Non-current assets | B89: Other non-current financial assets > 1 y | C89: Loans | D89: Loans > 1 y - N | E89: 15240 | F89: =IFERROR(VLOOKUP(E89,'[9]SAP Input-BS'!$A$5:$F$502,5,0),0) -> 0 | G89: =IFERROR(VLOOKUP(E89,'[10]SAP Input-BS'!$A$5:$F$500,5,0),0) -> 0 | H89: =F89-G89 -> 0 | K89: =IFERROR(VLOOKUP(E89,'[11]SAP Input-BS'!$A$5:$E$500,5,0),0) -> 0 | L89: 0
A90: Non-current assets | B90: Other non-current financial assets > 1 y | C90: Loans | D90: Loans > 1 y - B-a | E90: 15260 | F90: =IFERROR(VLOOKUP(E90,'[9]SAP Input-BS'!$A$5:$F$502,5,0),0) -> 0 | G90: =IFERROR(VLOOKUP(E90,'[10]SAP Input-BS'!$A$5:$F$500,5,0),0) -> 0 | H90: =F90-G90 -> 0 | K90: =IFERROR(VLOOKUP(E90,'[11]SAP Input-BS'!$A$5:$E$500,5,0),0) -> 0 | L90: 0
A91: Non-current assets | B91: Other non-current financial assets > 1 y | C91: Loans | D91: Loans FVPL (not SPPI compliant) > 1 y - 3rd, B-c, B-f | E91: 15280 | F91: =IFERROR(VLOOKUP(E91,'[9]SAP Input-BS'!$A$5:$F$502,5,0),0) -> 0 | G91: =IFERROR(VLOOKUP(E91,'[10]SAP Input-BS'!$A$5:$F$500,5,0),0) -> 0 | H91: =F91-G91 -> 0 | K91: =IFERROR(VLOOKUP(E91,'[11]SAP Input-BS'!$A$5:$E$500,5,0),0) -> 0 | L91: 0
A92: Non-current assets | B92: Other non-current financial assets > 1 y | C92: Loans > 1 y | D92: Total: Loans > 1 y | E92: 15289 | F92: =IFERROR(VLOOKUP(E92,'[9]SAP Input-BS'!$A$5:$F$502,5,0),0) -> 9.7119364e+08 | G92: =IFERROR(VLOOKUP(E92,'[10]SAP Input-BS'!$A$5:$F$500,5,0),0) -> 5.8936929e+08 | H92: =F92-G92 -> 381824348 | K92: =IFERROR(VLOOKUP(E92,'[11]SAP Input-BS'!$A$5:$E$500,5,0),0) -> 3.9383575e+08 | L92: 5.3321127e+08
A93: Non-current assets | B93: Other non-current financial assets > 1 y | D93: Derivatives w/o hedge > 1 y - 3rd | E93: 15303 | F93: =IFERROR(VLOOKUP(E93,'[9]SAP Input-BS'!$A$5:$F$502,5,0),0) -> 0 | G93: =IFERROR(VLOOKUP(E93,'[10]SAP Input-BS'!$A$5:$F$500,5,0),0) -> 0 | H93: =F93-G93 -> 0 | K93: =IFERROR(VLOOKUP(E93,'[11]SAP Input-BS'!$A$5:$E$500,5,0),0) -> 0 | L93: 0
A94: Non-current assets | B94: Other non-current financial assets > 1 y | D94: Receivables from finance lease (lessor) > 1 y | E94: 15305 | F94: =IFERROR(VLOOKUP(E94,'[9]SAP Input-BS'!$A$5:$F$502,5,0),0) -> 1.2121761e+08 | G94: =IFERROR(VLOOKUP(E94,'[10]SAP Input-BS'!$A$5:$F$500,5,0),0) -> 2.1593458e+08 | H94: =F94-G94 -> -94716963 | K94: =IFERROR(VLOOKUP(E94,'[11]SAP Input-BS'!$A$5:$E$500,5,0),0) -> -0.01 | L94: 3.1928369e+08
A95: Non-current assets | B95: Other non-current financial assets > 1 y | D95: Other financial receivables > 1 y - 3rd, B-c, B-f | E95: 15312 | F95: =IFERROR(VLOOKUP(E95,'[9]SAP Input-BS'!$A$5:$F$502,5,0),0) -> 1270728058 | G95: =IFERROR(VLOOKUP(E95,'[10]SAP Input-BS'!$A$5:$F$500,5,0),0) -> 1498295348 | H95: =F95-G95 -> -227567290 | K95: =IFERROR(VLOOKUP(E95,'[11]SAP Input-BS'!$A$5:$E$500,5,0),0) -> 1627141058 | L95: 1.5000577e+09
A96: Non-current assets | B96: Other non-current financial assets > 1 y | D96: Other financial receivables > 1 y - K | E96: 15322 | F96: =IFERROR(VLOOKUP(E96,'[9]SAP Input-BS'!$A$5:$F$502,5,0),0) -> 0 | G96: =IFERROR(VLOOKUP(E96,'[10]SAP Input-BS'!$A$5:$F$500,5,0),0) -> 0 | H96: =F96-G96 -> 0 | K96: =IFERROR(VLOOKUP(E96,'[11]SAP Input-BS'!$A$5:$E$500,5,0),0) -> 0 | L96: 0
A97: Non-current assets | B97: Other non-current financial assets > 1 y | D97: Other financial receivables > 1 y - N | E97: 15342 | F97: =IFERROR(VLOOKUP(E97,'[9]SAP Input-BS'!$A$5:$F$502,5,0),0) -> 0 | G97: =IFERROR(VLOOKUP(E97,'[10]SAP Input-BS'!$A$5:$F$500,5,0),0) -> 0 | H97: =F97-G97 -> 0 | K97: =IFERROR(VLOOKUP(E97,'[11]SAP Input-BS'!$A$5:$E$500,5,0),0) -> 0 | L97: 0
A98: Non-current assets | B98: Other non-current financial assets > 1 y | D98: Other financial receivables > 1 y - B-a | E98: 15362 | F98: =IFERROR(VLOOKUP(E98,'[9]SAP Input-BS'!$A$5:$F$502,5,0),0) -> 0 | G98: =IFERROR(VLOOKUP(E98,'[10]SAP Input-BS'!$A$5:$F$500,5,0),0) -> 0 | H98: =F98-G98 -> 0 | K98: =IFERROR(VLOOKUP(E98,'[11]SAP Input-BS'!$A$5:$E$500,5,0),0) -> 0 | L98: 0
A99: Non-current assets | B99: Other non-current financial assets > 1 y | C99: Other non-current financial assets > 1 y | D99: Total: other non-current financial assets > 1 y | E99: AN_FA | F99: =IFERROR(VLOOKUP(E99,'[9]SAP Input-BS'!$A$5:$F$502,5,0),0) -> 1.7505931e+10 | G99: =IFERROR(VLOOKUP(E99,'[10]SAP Input-BS'!$A$5:$F$500,5,0),0) -> 2.11344e+10 | H99: =F99-G99 -> -3628469103 | K99: =IFERROR(VLOOKUP(E99,'[11]SAP Input-BS'!$A$5:$E$500,5,0),0) -> 1.6598624e+10 | L99: 2.0748968e+10
A100: Non-current assets | B100: Contract assets (CA) > 1 y | D100: CA: Sales over time > 1 y - 3rd, N, B-a, B-c, B-f | E100: 15500 | F100: =IFERROR(VLOOKUP(E100,'[9]SAP Input-BS'!$A$5:$F$502,5,0),0) -> 8.5917313e+08 | G100: =IFERROR(VLOOKUP(E100,'[10]SAP Input-BS'!$A$5:$F$500,5,0),0) -> 8.5917313e+08 | H100: =F100-G100 -> 0 | J100: GMR Unbilled | K100: =IFERROR(VLOOKUP(E100,'[11]SAP Input-BS'!$A$5:$E$500,5,0),0) -> 0 | L100: 0
A101: Non-current assets | B101: Contract assets (CA) > 1 y | D101: CA: Other > 1 y - 3rd, N, B-a, B-c, B-f | E101: 15501 | F101: =IFERROR(VLOOKUP(E101,'[9]SAP Input-BS'!$A$5:$F$502,5,0),0) -> 0 | G101: =IFERROR(VLOOKUP(E101,'[10]SAP Input-BS'!$A$5:$F$500,5,0),0) -> 0 | H101: =F101-G101 -> 0 | K101: =IFERROR(VLOOKUP(E101,'[11]SAP Input-BS'!$A$5:$E$500,5,0),0) -> 0 | L101: 0
A102: Non-current assets | B102: Contract assets (CA) > 1 y | D102: CA: R&D contracts > 1 y - 3rd, B-a, B-c, B-f | E102: 15504 | F102: =IFERROR(VLOOKUP(E102,'[9]SAP Input-BS'!$A$5:$F$502,5,0),0) -> 0 | G102: =IFERROR(VLOOKUP(E102,'[10]SAP Input-BS'!$A$5:$F$500,5,0),0) -> 0 | H102: =F102-G102 -> 0 | K102: =IFERROR(VLOOKUP(E102,'[11]SAP Input-BS'!$A$5:$E$500,5,0),0) -> 0 | L102: 0
A103: Non-current assets | B103: Contract assets (CA) > 1 y | D103: CA: R&D contracts > 1 y - N | E103: 15540 | F103: =IFERROR(VLOOKUP(E103,'[9]SAP Input-BS'!$A$5:$F$502,5,0),0) -> 0 | G103: =IFERROR(VLOOKUP(E103,'[10]SAP Input-BS'!$A$5:$F$500,5,0),0) -> 0 | H103: =F103-G103 -> 0 | K103: =IFERROR(VLOOKUP(E103,'[11]SAP Input-BS'!$A$5:$E$500,5,0),0) -> 0 | L103: 0
...

Sheet Sheet2
A2: Assets | B2: Why has cash reduced so much | G2: ='BS-Assets'!G4 -> 1560768050 | H2: =G2/87/10^6 -> 17.939863 | J2: =#REF! -> #REF! | K2: =H2-J2 -> #REF!
B3: SDS Invesmtnet | G3: =-10*10^7 -> -100000000 | H3: =G3/87/10^6 -> -1.1494253 | K3: =H3 -> -1.1494253
B4: AI Shield Investment | G4: =-33*10^7 -> -330000000 | H4: =G4/87/10^6 -> -3.7931034 | K4: =H4 -> -3.7931034
B5: Advance Tax Payent | G5: =-3220*10^6 -> -3220000000 | H5: =G5/87/10^6 -> -37.011494 | K5: =H5 -> -37.011494
B6: Excess payments vs Lower collection | K6: -93
B7: Escrow relevae Johnson Controls | K7: =[13]Cashflow_2026_Collection_wise!$D$16/87 -> 100.49446
B8: Bonus Payouts | K8: -40.229885
K9: =SUM(K2:K8) -> #REF!
B10: Trade receivables break up | G10: =SUM(G2:G6) -> -2089231950
B11: ICR | G11: ='BS-Assets'!F4 -> 1.2020967e+10
B12: SDS | G12: =G10-G11 -> -1.4110199e+10
B14: Marketable securities - Schedule
B15: MTM (FVTPL done in March'26 and Mar'25)
B17: Fin. receivables board members, employees ≤ 1 y
B18: Other financial receivables ≤ 1 year third parties, B-c, B-f
B20: Other financial receivables ≤ 1 y - B-a
B21: How its so low and negative sign in Assets
B23: Total: Investments (wo B-a)
B24: SDS and AI shield
B26: Contract assets (CA) > 1 y | D26: CA: Sales over time > 1 y - 3rd, N, B-a, B-c, B-f
B28: CWIP ageing
B30: Other tax receivables > 1 year
A32: Liabilities | B32: Trade Payables - old balances Split
B34: Other financial liabilities ≤ 1 y - 3rd, B-c, B-f | C34: 21318
B36: Financial liabil. to board members, employees ≤ 1 y
B38: CL: Sales over time ≤ 1 y - 3rd, N, B-a, B-c, B-f | C38: 20200
B40: Liabil. to board members, employees ≤ 1 y | C40: 21390
B41: Liabil. to board memb., employees > 1 y
B43: Personnel related provisions > 1 y
B44: Personnel related provisions < 1 y
